package com.whatsapp.m;

import com.whatsapp.MediaData;
import com.whatsapp.ai;
import com.whatsapp.fieldstats.events.au;
import com.whatsapp.i.a.a;
import com.whatsapp.l.h;
import com.whatsapp.protocol.j;
import com.whatsapp.util.a.c;
import com.whatsapp.vk;
import com.whatsapp.vk.b;
import com.whatsapp.vv;
import java.io.File;
import java.io.IOException;
import java.io.InputStream;
import java.net.URL;

public final class e
{
  public final a a;
  public vk.b b;
  public final au c;
  public Exception d;
  private byte[] e;
  private final com.whatsapp.d.d f;
  private final vk g;
  private final j h;
  private final MediaData i;
  private final URL j;
  private final File k;
  private final File l;
  private final File m;
  private d n;
  private h o;
  private final c p;
  private final vv q;
  private final ai r;
  private final com.whatsapp.i.a s;
  
  public e(c paramc, vv paramvv, ai paramai, a parama, byte[] paramArrayOfByte, j paramj, URL paramURL, File paramFile1, File paramFile2, File paramFile3, vk paramvk, com.whatsapp.i.a parama1, h paramh)
  {
    this.p = paramc;
    this.q = paramvv;
    this.r = paramai;
    this.e = paramArrayOfByte;
    this.h = paramj;
    this.i = paramj.b();
    this.s = parama1;
    this.f = new com.whatsapp.d.d(this.i.cipherKey, this.i.hmacKey, this.i.iv, this.i.refKey);
    this.g = paramvk;
    this.a = parama;
    this.j = paramURL;
    this.k = paramFile1;
    this.l = paramFile2;
    this.m = paramFile3;
    this.c = new au();
    this.c.j = Integer.valueOf(0);
    this.o = paramh;
  }
  
  private a.a a(URL paramURL, long paramLong1, long paramLong2)
  {
    paramURL = com.whatsapp.i.a.a(this.i, paramURL, paramLong1, paramLong2, this.o);
    if (this.b == null) {
      this.b = new vk.b(paramURL.a("X-WA-Metadata"));
    }
    return paramURL;
  }
  
  private static byte[] a(InputStream paramInputStream)
  {
    byte[] arrayOfByte = new byte[16];
    int i1 = 0;
    while (i1 < 16)
    {
      int i2 = paramInputStream.read(arrayOfByte, i1, 16 - i1);
      if (i2 == -1) {
        throw new IOException("attempting to read end of file");
      }
      i1 += i2;
    }
    return arrayOfByte;
  }
  
  /* Error */
  public final com.whatsapp.vk.d a()
  {
    // Byte code:
    //   0: aload_0
    //   1: getfield 97	com/whatsapp/m/e:k	Ljava/io/File;
    //   4: invokevirtual 163	java/io/File:exists	()Z
    //   7: ifne +11 -> 18
    //   10: aload_0
    //   11: getfield 97	com/whatsapp/m/e:k	Ljava/io/File;
    //   14: invokevirtual 166	java/io/File:createNewFile	()Z
    //   17: pop
    //   18: aload_0
    //   19: getfield 99	com/whatsapp/m/e:l	Ljava/io/File;
    //   22: invokevirtual 163	java/io/File:exists	()Z
    //   25: ifne +11 -> 36
    //   28: aload_0
    //   29: getfield 99	com/whatsapp/m/e:l	Ljava/io/File;
    //   32: invokevirtual 166	java/io/File:createNewFile	()Z
    //   35: pop
    //   36: aload_0
    //   37: getfield 91	com/whatsapp/m/e:g	Lcom/whatsapp/vk;
    //   40: getfield 171	com/whatsapp/vk:f	Lcom/whatsapp/vk$a;
    //   43: getstatic 175	com/whatsapp/vk$a:b	Lcom/whatsapp/vk$a;
    //   46: if_acmpne +41 -> 87
    //   49: aload_0
    //   50: getfield 55	com/whatsapp/m/e:r	Lcom/whatsapp/ai;
    //   53: aload_0
    //   54: getfield 59	com/whatsapp/m/e:h	Lcom/whatsapp/protocol/j;
    //   57: invokevirtual 180	com/whatsapp/ai:c	(Lcom/whatsapp/protocol/j;)Z
    //   60: ifne +27 -> 87
    //   63: ldc -74
    //   65: invokestatic 186	com/whatsapp/util/Log:i	(Ljava/lang/String;)V
    //   68: getstatic 191	com/whatsapp/vk$d:l	Lcom/whatsapp/vk$d;
    //   71: astore 16
    //   73: aload 16
    //   75: areturn
    //   76: astore 15
    //   78: ldc -63
    //   80: invokestatic 196	com/whatsapp/util/Log:w	(Ljava/lang/String;)V
    //   83: getstatic 198	com/whatsapp/vk$d:a	Lcom/whatsapp/vk$d;
    //   86: areturn
    //   87: aload_0
    //   88: getfield 91	com/whatsapp/m/e:g	Lcom/whatsapp/vk;
    //   91: getfield 171	com/whatsapp/vk:f	Lcom/whatsapp/vk$a;
    //   94: getstatic 200	com/whatsapp/vk$a:c	Lcom/whatsapp/vk$a;
    //   97: if_acmpne +43 -> 140
    //   100: aload_0
    //   101: getfield 55	com/whatsapp/m/e:r	Lcom/whatsapp/ai;
    //   104: astore 15
    //   106: aload_0
    //   107: getfield 59	com/whatsapp/m/e:h	Lcom/whatsapp/protocol/j;
    //   110: astore 16
    //   112: aload 15
    //   114: aload 15
    //   116: getfield 203	com/whatsapp/ai:a	Lcom/whatsapp/aat;
    //   119: iconst_0
    //   120: invokevirtual 208	com/whatsapp/aat:a	(Z)I
    //   123: aload 16
    //   125: invokevirtual 211	com/whatsapp/ai:c	(ILcom/whatsapp/protocol/j;)Z
    //   128: ifne +12 -> 140
    //   131: ldc -43
    //   133: invokestatic 186	com/whatsapp/util/Log:i	(Ljava/lang/String;)V
    //   136: getstatic 215	com/whatsapp/vk$d:m	Lcom/whatsapp/vk$d;
    //   139: areturn
    //   140: aload_0
    //   141: new 217	com/whatsapp/m/d
    //   144: dup
    //   145: aload_0
    //   146: getfield 51	com/whatsapp/m/e:p	Lcom/whatsapp/util/a/c;
    //   149: aload_0
    //   150: getfield 99	com/whatsapp/m/e:l	Ljava/io/File;
    //   153: aload_0
    //   154: getfield 93	com/whatsapp/m/e:a	Lcom/whatsapp/m/a;
    //   157: invokevirtual 222	com/whatsapp/m/a:i	()J
    //   160: invokespecial 225	com/whatsapp/m/d:<init>	(Lcom/whatsapp/util/a/c;Ljava/io/File;J)V
    //   163: putfield 227	com/whatsapp/m/e:n	Lcom/whatsapp/m/d;
    //   166: aconst_null
    //   167: astore 15
    //   169: lconst_0
    //   170: lstore 4
    //   172: aload 15
    //   174: astore 20
    //   176: aload_0
    //   177: getfield 99	com/whatsapp/m/e:l	Ljava/io/File;
    //   180: invokevirtual 230	java/io/File:length	()J
    //   183: lconst_0
    //   184: lcmp
    //   185: ifle +31 -> 216
    //   188: aload 15
    //   190: astore 20
    //   192: aload_0
    //   193: getfield 101	com/whatsapp/m/e:m	Ljava/io/File;
    //   196: invokevirtual 163	java/io/File:exists	()Z
    //   199: ifeq +17 -> 216
    //   202: ldc -24
    //   204: invokestatic 186	com/whatsapp/util/Log:i	(Ljava/lang/String;)V
    //   207: aload_0
    //   208: getfield 101	com/whatsapp/m/e:m	Ljava/io/File;
    //   211: invokestatic 237	com/whatsapp/m/b:b	(Ljava/io/File;)Lcom/whatsapp/m/b;
    //   214: astore 20
    //   216: aload_0
    //   217: getfield 93	com/whatsapp/m/e:a	Lcom/whatsapp/m/a;
    //   220: getstatic 242	com/whatsapp/m/a$a:a	Lcom/whatsapp/m/a$a;
    //   223: invokevirtual 245	com/whatsapp/m/a:a	(Lcom/whatsapp/m/a$a;)V
    //   226: aload 20
    //   228: ifnonnull +292 -> 520
    //   231: aload_0
    //   232: aload_0
    //   233: getfield 95	com/whatsapp/m/e:j	Ljava/net/URL;
    //   236: lconst_0
    //   237: ldc2_w 246
    //   240: invokespecial 249	com/whatsapp/m/e:a	(Ljava/net/URL;JJ)Lcom/whatsapp/i/a$a;
    //   243: astore 15
    //   245: aload 15
    //   247: astore 16
    //   249: aload 15
    //   251: astore 17
    //   253: aload 15
    //   255: astore 19
    //   257: aload 15
    //   259: astore 18
    //   261: aload 15
    //   263: invokevirtual 251	com/whatsapp/i/a$a:a	()J
    //   266: lstore 6
    //   268: aload 15
    //   270: astore 16
    //   272: aload 15
    //   274: astore 17
    //   276: aload 15
    //   278: astore 19
    //   280: aload 15
    //   282: astore 18
    //   284: new 234	com/whatsapp/m/b
    //   287: dup
    //   288: lload 6
    //   290: invokespecial 254	com/whatsapp/m/b:<init>	(J)V
    //   293: astore 29
    //   295: aload 15
    //   297: astore 16
    //   299: aload 15
    //   301: astore 17
    //   303: aload 15
    //   305: astore 19
    //   307: aload 15
    //   309: astore 18
    //   311: aload_0
    //   312: getfield 93	com/whatsapp/m/e:a	Lcom/whatsapp/m/a;
    //   315: aload_0
    //   316: getfield 101	com/whatsapp/m/e:m	Ljava/io/File;
    //   319: aload 29
    //   321: invokevirtual 257	com/whatsapp/m/a:a	(Ljava/io/File;Lcom/whatsapp/m/b;)V
    //   324: aload 15
    //   326: astore 16
    //   328: aload 15
    //   330: astore 17
    //   332: aload 15
    //   334: astore 19
    //   336: aload 15
    //   338: astore 18
    //   340: aload_0
    //   341: getfield 106	com/whatsapp/m/e:c	Lcom/whatsapp/fieldstats/events/au;
    //   344: iconst_0
    //   345: invokestatic 262	java/lang/Boolean:valueOf	(Z)Ljava/lang/Boolean;
    //   348: putfield 265	com/whatsapp/fieldstats/events/au:d	Ljava/lang/Boolean;
    //   351: aload 15
    //   353: astore 16
    //   355: aload 15
    //   357: astore 17
    //   359: aload 15
    //   361: astore 19
    //   363: aload 15
    //   365: astore 18
    //   367: aload_0
    //   368: getfield 93	com/whatsapp/m/e:a	Lcom/whatsapp/m/a;
    //   371: getstatic 267	com/whatsapp/m/a$a:b	Lcom/whatsapp/m/a$a;
    //   374: invokevirtual 245	com/whatsapp/m/a:a	(Lcom/whatsapp/m/a$a;)V
    //   377: aload 15
    //   379: astore 16
    //   381: aload 15
    //   383: astore 17
    //   385: aload 15
    //   387: astore 19
    //   389: aload 15
    //   391: astore 18
    //   393: new 269	com/whatsapp/d/e
    //   396: dup
    //   397: aload_0
    //   398: getfield 97	com/whatsapp/m/e:k	Ljava/io/File;
    //   401: aload_0
    //   402: getfield 99	com/whatsapp/m/e:l	Ljava/io/File;
    //   405: aload_0
    //   406: getfield 57	com/whatsapp/m/e:e	[B
    //   409: aload_0
    //   410: getfield 89	com/whatsapp/m/e:f	Lcom/whatsapp/d/d;
    //   413: lload 6
    //   415: invokespecial 272	com/whatsapp/d/e:<init>	(Ljava/io/File;Ljava/io/File;[BLcom/whatsapp/d/d;J)V
    //   418: astore 21
    //   420: aload_0
    //   421: getfield 106	com/whatsapp/m/e:c	Lcom/whatsapp/fieldstats/events/au;
    //   424: lload 6
    //   426: invokestatic 277	java/lang/Long:valueOf	(J)Ljava/lang/Long;
    //   429: putfield 280	com/whatsapp/fieldstats/events/au:b	Ljava/lang/Long;
    //   432: invokestatic 284	com/whatsapp/vv:f	()J
    //   435: ldc2_w 285
    //   438: lload 6
    //   440: lmul
    //   441: lcmp
    //   442: ifge +293 -> 735
    //   445: ldc_w 288
    //   448: invokestatic 196	com/whatsapp/util/Log:w	(Ljava/lang/String;)V
    //   451: new 6	com/whatsapp/m/e$a
    //   454: dup
    //   455: iconst_0
    //   456: invokespecial 291	com/whatsapp/m/e$a:<init>	(B)V
    //   459: athrow
    //   460: astore 16
    //   462: aconst_null
    //   463: astore 16
    //   465: aconst_null
    //   466: astore 17
    //   468: getstatic 293	com/whatsapp/vk$d:e	Lcom/whatsapp/vk$d;
    //   471: astore 18
    //   473: aload 17
    //   475: ifnull +8 -> 483
    //   478: aload 17
    //   480: invokevirtual 298	java/io/RandomAccessFile:close	()V
    //   483: aload 16
    //   485: ifnull +8 -> 493
    //   488: aload 16
    //   490: invokevirtual 299	java/io/InputStream:close	()V
    //   493: aload 15
    //   495: ifnull +8 -> 503
    //   498: aload 15
    //   500: invokestatic 304	a/a/a/a/a/a$d:a	(Ljava/io/Closeable;)V
    //   503: aload 18
    //   505: astore 16
    //   507: aload 21
    //   509: ifnull -436 -> 73
    //   512: aload 21
    //   514: invokevirtual 306	com/whatsapp/d/e:b	()V
    //   517: aload 18
    //   519: areturn
    //   520: new 308	java/lang/StringBuilder
    //   523: dup
    //   524: ldc_w 310
    //   527: invokespecial 311	java/lang/StringBuilder:<init>	(Ljava/lang/String;)V
    //   530: aload 20
    //   532: invokevirtual 313	com/whatsapp/m/b:b	()J
    //   535: invokevirtual 317	java/lang/StringBuilder:append	(J)Ljava/lang/StringBuilder;
    //   538: invokevirtual 321	java/lang/StringBuilder:toString	()Ljava/lang/String;
    //   541: invokestatic 186	com/whatsapp/util/Log:i	(Ljava/lang/String;)V
    //   544: aload_0
    //   545: getfield 93	com/whatsapp/m/e:a	Lcom/whatsapp/m/a;
    //   548: aload_0
    //   549: getfield 101	com/whatsapp/m/e:m	Ljava/io/File;
    //   552: aload 20
    //   554: invokevirtual 257	com/whatsapp/m/a:a	(Ljava/io/File;Lcom/whatsapp/m/b;)V
    //   557: aload 20
    //   559: getfield 324	com/whatsapp/m/b:a	J
    //   562: lstore 6
    //   564: aload 20
    //   566: lconst_0
    //   567: invokevirtual 327	com/whatsapp/m/b:a	(J)J
    //   570: lstore 4
    //   572: aload_0
    //   573: getfield 93	com/whatsapp/m/e:a	Lcom/whatsapp/m/a;
    //   576: aload 20
    //   578: invokevirtual 313	com/whatsapp/m/b:b	()J
    //   581: invokevirtual 329	com/whatsapp/m/a:a	(J)V
    //   584: aload_0
    //   585: getfield 93	com/whatsapp/m/e:a	Lcom/whatsapp/m/a;
    //   588: aload 20
    //   590: invokevirtual 313	com/whatsapp/m/b:b	()J
    //   593: invokevirtual 331	com/whatsapp/m/a:b	(J)V
    //   596: lload 4
    //   598: lconst_0
    //   599: lcmp
    //   600: iflt +56 -> 656
    //   603: aload_0
    //   604: aload_0
    //   605: getfield 95	com/whatsapp/m/e:j	Ljava/net/URL;
    //   608: lload 4
    //   610: aload 20
    //   612: lload 4
    //   614: invokevirtual 333	com/whatsapp/m/b:c	(J)J
    //   617: invokespecial 249	com/whatsapp/m/e:a	(Ljava/net/URL;JJ)Lcom/whatsapp/i/a$a;
    //   620: astore 15
    //   622: aload 15
    //   624: astore 16
    //   626: aload 15
    //   628: astore 17
    //   630: aload 15
    //   632: astore 19
    //   634: aload 15
    //   636: astore 18
    //   638: aload_0
    //   639: getfield 106	com/whatsapp/m/e:c	Lcom/whatsapp/fieldstats/events/au;
    //   642: iconst_1
    //   643: invokestatic 262	java/lang/Boolean:valueOf	(Z)Ljava/lang/Boolean;
    //   646: putfield 265	com/whatsapp/fieldstats/events/au:d	Ljava/lang/Boolean;
    //   649: aload 20
    //   651: astore 29
    //   653: goto -302 -> 351
    //   656: aload_0
    //   657: aload_0
    //   658: getfield 95	com/whatsapp/m/e:j	Ljava/net/URL;
    //   661: lconst_0
    //   662: ldc2_w 246
    //   665: invokespecial 249	com/whatsapp/m/e:a	(Ljava/net/URL;JJ)Lcom/whatsapp/i/a$a;
    //   668: astore 15
    //   670: goto -48 -> 622
    //   673: astore 16
    //   675: aload 15
    //   677: astore 16
    //   679: aload 15
    //   681: astore 17
    //   683: aload 15
    //   685: astore 19
    //   687: aload 15
    //   689: astore 18
    //   691: ldc_w 335
    //   694: invokestatic 196	com/whatsapp/util/Log:w	(Ljava/lang/String;)V
    //   697: aload 15
    //   699: astore 16
    //   701: aload 15
    //   703: astore 17
    //   705: aload 15
    //   707: astore 19
    //   709: aload 15
    //   711: astore 18
    //   713: getstatic 198	com/whatsapp/vk$d:a	Lcom/whatsapp/vk$d;
    //   716: astore 20
    //   718: aload 20
    //   720: astore 16
    //   722: aload 15
    //   724: ifnull -651 -> 73
    //   727: aload 15
    //   729: invokestatic 304	a/a/a/a/a/a$d:a	(Ljava/io/Closeable;)V
    //   732: aload 20
    //   734: areturn
    //   735: aload 29
    //   737: invokevirtual 313	com/whatsapp/m/b:b	()J
    //   740: lstore 8
    //   742: aload_0
    //   743: getfield 91	com/whatsapp/m/e:g	Lcom/whatsapp/vk;
    //   746: getfield 171	com/whatsapp/vk:f	Lcom/whatsapp/vk$a;
    //   749: getstatic 200	com/whatsapp/vk$a:c	Lcom/whatsapp/vk$a;
    //   752: if_acmpne +41 -> 793
    //   755: lload 8
    //   757: ldc2_w 336
    //   760: lcmp
    //   761: ifle +32 -> 793
    //   764: ldc_w 339
    //   767: invokestatic 186	com/whatsapp/util/Log:i	(Ljava/lang/String;)V
    //   770: getstatic 215	com/whatsapp/vk$d:m	Lcom/whatsapp/vk$d;
    //   773: astore 16
    //   775: aload 15
    //   777: ifnull +8 -> 785
    //   780: aload 15
    //   782: invokestatic 304	a/a/a/a/a/a$d:a	(Ljava/io/Closeable;)V
    //   785: aload 21
    //   787: invokevirtual 306	com/whatsapp/d/e:b	()V
    //   790: aload 16
    //   792: areturn
    //   793: aload_0
    //   794: getfield 106	com/whatsapp/m/e:c	Lcom/whatsapp/fieldstats/events/au;
    //   797: lload 8
    //   799: invokestatic 277	java/lang/Long:valueOf	(J)Ljava/lang/Long;
    //   802: putfield 341	com/whatsapp/fieldstats/events/au:e	Ljava/lang/Long;
    //   805: new 295	java/io/RandomAccessFile
    //   808: dup
    //   809: aload_0
    //   810: getfield 97	com/whatsapp/m/e:k	Ljava/io/File;
    //   813: ldc_w 343
    //   816: invokespecial 346	java/io/RandomAccessFile:<init>	(Ljava/io/File;Ljava/lang/String;)V
    //   819: astore 17
    //   821: lload 4
    //   823: lconst_0
    //   824: lcmp
    //   825: iflt +4868 -> 5693
    //   828: aload 17
    //   830: lload 4
    //   832: invokevirtual 349	java/io/RandomAccessFile:seek	(J)V
    //   835: aload 15
    //   837: getfield 352	com/whatsapp/i/a$a:a	Ljavax/net/ssl/HttpsURLConnection;
    //   840: invokevirtual 358	javax/net/ssl/HttpsURLConnection:getInputStream	()Ljava/io/InputStream;
    //   843: astore 16
    //   845: aload_0
    //   846: getfield 59	com/whatsapp/m/e:h	Lcom/whatsapp/protocol/j;
    //   849: invokevirtual 360	com/whatsapp/protocol/j:a	()Z
    //   852: ifeq +1086 -> 1938
    //   855: iconst_4
    //   856: istore_1
    //   857: new 362	com/whatsapp/Statistics$a
    //   860: dup
    //   861: aload 16
    //   863: iload_1
    //   864: invokespecial 365	com/whatsapp/Statistics$a:<init>	(Ljava/io/InputStream;I)V
    //   867: astore 16
    //   869: aload 15
    //   871: astore 26
    //   873: aload 16
    //   875: astore 28
    //   877: aload 21
    //   879: astore 23
    //   881: aload 15
    //   883: astore 20
    //   885: aload 16
    //   887: astore 19
    //   889: aload 17
    //   891: astore 22
    //   893: aload 15
    //   895: astore 27
    //   897: aload 16
    //   899: astore 24
    //   901: aload 15
    //   903: astore 25
    //   905: aload 16
    //   907: astore 18
    //   909: sipush 8192
    //   912: newarray <illegal type>
    //   914: astore 31
    //   916: lload 4
    //   918: lstore 6
    //   920: lload 8
    //   922: lstore 4
    //   924: lload 6
    //   926: lconst_0
    //   927: lcmp
    //   928: iflt +3434 -> 4362
    //   931: aload 15
    //   933: astore 26
    //   935: aload 16
    //   937: astore 28
    //   939: aload 21
    //   941: astore 23
    //   943: aload 15
    //   945: astore 20
    //   947: aload 16
    //   949: astore 19
    //   951: aload 17
    //   953: astore 22
    //   955: aload 15
    //   957: astore 27
    //   959: aload 16
    //   961: astore 24
    //   963: aload 15
    //   965: astore 25
    //   967: aload 16
    //   969: astore 18
    //   971: aload 16
    //   973: aload 31
    //   975: iconst_0
    //   976: sipush 8192
    //   979: invokevirtual 145	java/io/InputStream:read	([BII)I
    //   982: istore_1
    //   983: iload_1
    //   984: iflt +4706 -> 5690
    //   987: aload 15
    //   989: astore 26
    //   991: aload 16
    //   993: astore 28
    //   995: aload 21
    //   997: astore 23
    //   999: aload 15
    //   1001: astore 20
    //   1003: aload 16
    //   1005: astore 19
    //   1007: aload 17
    //   1009: astore 22
    //   1011: aload 15
    //   1013: astore 27
    //   1015: aload 16
    //   1017: astore 24
    //   1019: aload 15
    //   1021: astore 25
    //   1023: aload 16
    //   1025: astore 18
    //   1027: aload 17
    //   1029: aload 31
    //   1031: iconst_0
    //   1032: iload_1
    //   1033: invokevirtual 369	java/io/RandomAccessFile:write	([BII)V
    //   1036: aload 15
    //   1038: astore 26
    //   1040: aload 16
    //   1042: astore 28
    //   1044: aload 21
    //   1046: astore 23
    //   1048: aload 15
    //   1050: astore 20
    //   1052: aload 16
    //   1054: astore 19
    //   1056: aload 17
    //   1058: astore 22
    //   1060: aload 15
    //   1062: astore 27
    //   1064: aload 16
    //   1066: astore 24
    //   1068: aload 15
    //   1070: astore 25
    //   1072: aload 16
    //   1074: astore 18
    //   1076: aload 17
    //   1078: invokevirtual 373	java/io/RandomAccessFile:getFD	()Ljava/io/FileDescriptor;
    //   1081: invokevirtual 378	java/io/FileDescriptor:sync	()V
    //   1084: aload 15
    //   1086: astore 26
    //   1088: aload 16
    //   1090: astore 28
    //   1092: aload 21
    //   1094: astore 23
    //   1096: aload 15
    //   1098: astore 20
    //   1100: aload 16
    //   1102: astore 19
    //   1104: aload 17
    //   1106: astore 22
    //   1108: aload 15
    //   1110: astore 27
    //   1112: aload 16
    //   1114: astore 24
    //   1116: aload 15
    //   1118: astore 25
    //   1120: aload 16
    //   1122: astore 18
    //   1124: aload 29
    //   1126: lload 6
    //   1128: iload_1
    //   1129: i2l
    //   1130: iconst_0
    //   1131: invokevirtual 381	com/whatsapp/m/b:a	(JJZ)Ljava/util/List;
    //   1134: astore 30
    //   1136: aload 15
    //   1138: astore 26
    //   1140: aload 16
    //   1142: astore 28
    //   1144: aload 21
    //   1146: astore 23
    //   1148: aload 15
    //   1150: astore 20
    //   1152: aload 16
    //   1154: astore 19
    //   1156: aload 17
    //   1158: astore 22
    //   1160: aload 15
    //   1162: astore 27
    //   1164: aload 16
    //   1166: astore 24
    //   1168: aload 15
    //   1170: astore 25
    //   1172: aload 16
    //   1174: astore 18
    //   1176: aload 30
    //   1178: invokeinterface 386 1 0
    //   1183: ifne +1239 -> 2422
    //   1186: aload 15
    //   1188: astore 26
    //   1190: aload 16
    //   1192: astore 28
    //   1194: aload 21
    //   1196: astore 23
    //   1198: aload 15
    //   1200: astore 20
    //   1202: aload 16
    //   1204: astore 19
    //   1206: aload 17
    //   1208: astore 22
    //   1210: aload 15
    //   1212: astore 27
    //   1214: aload 16
    //   1216: astore 24
    //   1218: aload 15
    //   1220: astore 25
    //   1222: aload 16
    //   1224: astore 18
    //   1226: aload 30
    //   1228: invokeinterface 390 1 0
    //   1233: astore 32
    //   1235: aload 15
    //   1237: astore 26
    //   1239: aload 16
    //   1241: astore 28
    //   1243: aload 21
    //   1245: astore 23
    //   1247: aload 15
    //   1249: astore 20
    //   1251: aload 16
    //   1253: astore 19
    //   1255: aload 17
    //   1257: astore 22
    //   1259: aload 15
    //   1261: astore 27
    //   1263: aload 16
    //   1265: astore 24
    //   1267: aload 15
    //   1269: astore 25
    //   1271: aload 16
    //   1273: astore 18
    //   1275: aload 32
    //   1277: invokeinterface 395 1 0
    //   1282: ifeq +1140 -> 2422
    //   1285: aload 15
    //   1287: astore 26
    //   1289: aload 16
    //   1291: astore 28
    //   1293: aload 21
    //   1295: astore 23
    //   1297: aload 15
    //   1299: astore 20
    //   1301: aload 16
    //   1303: astore 19
    //   1305: aload 17
    //   1307: astore 22
    //   1309: aload 15
    //   1311: astore 27
    //   1313: aload 16
    //   1315: astore 24
    //   1317: aload 15
    //   1319: astore 25
    //   1321: aload 16
    //   1323: astore 18
    //   1325: aload 32
    //   1327: invokeinterface 399 1 0
    //   1332: checkcast 108	java/lang/Integer
    //   1335: invokevirtual 403	java/lang/Integer:intValue	()I
    //   1338: istore_3
    //   1339: iload_3
    //   1340: i2l
    //   1341: lstore 8
    //   1343: aload 15
    //   1345: astore 26
    //   1347: aload 16
    //   1349: astore 28
    //   1351: aload 21
    //   1353: astore 23
    //   1355: aload 15
    //   1357: astore 20
    //   1359: aload 16
    //   1361: astore 19
    //   1363: aload 17
    //   1365: astore 22
    //   1367: aload 15
    //   1369: astore 27
    //   1371: aload 16
    //   1373: astore 24
    //   1375: aload 15
    //   1377: astore 25
    //   1379: aload 16
    //   1381: astore 18
    //   1383: aload 29
    //   1385: getfield 405	com/whatsapp/m/b:b	J
    //   1388: lstore 10
    //   1390: aload 15
    //   1392: astore 26
    //   1394: aload 16
    //   1396: astore 28
    //   1398: aload 21
    //   1400: astore 23
    //   1402: aload 15
    //   1404: astore 20
    //   1406: aload 16
    //   1408: astore 19
    //   1410: aload 17
    //   1412: astore 22
    //   1414: aload 15
    //   1416: astore 27
    //   1418: aload 16
    //   1420: astore 24
    //   1422: aload 15
    //   1424: astore 25
    //   1426: aload 16
    //   1428: astore 18
    //   1430: aload 29
    //   1432: iload_3
    //   1433: invokevirtual 408	com/whatsapp/m/b:b	(I)I
    //   1436: i2l
    //   1437: lstore 12
    //   1439: aload 15
    //   1441: astore 26
    //   1443: aload 16
    //   1445: astore 28
    //   1447: aload 21
    //   1449: astore 23
    //   1451: aload 15
    //   1453: astore 20
    //   1455: aload 16
    //   1457: astore 19
    //   1459: aload 17
    //   1461: astore 22
    //   1463: aload 15
    //   1465: astore 27
    //   1467: aload 16
    //   1469: astore 24
    //   1471: aload 15
    //   1473: astore 25
    //   1475: aload 16
    //   1477: astore 18
    //   1479: aload 29
    //   1481: getfield 411	com/whatsapp/m/b:c	I
    //   1484: istore_2
    //   1485: iload_3
    //   1486: iload_2
    //   1487: iconst_1
    //   1488: isub
    //   1489: if_icmpne +503 -> 1992
    //   1492: iconst_1
    //   1493: istore 14
    //   1495: aload 21
    //   1497: astore 23
    //   1499: aload 15
    //   1501: astore 20
    //   1503: aload 16
    //   1505: astore 19
    //   1507: aload 17
    //   1509: astore 22
    //   1511: aload 15
    //   1513: astore 27
    //   1515: aload 16
    //   1517: astore 24
    //   1519: aload 15
    //   1521: astore 25
    //   1523: aload 16
    //   1525: astore 18
    //   1527: aload 21
    //   1529: lload 8
    //   1531: lload 10
    //   1533: lmul
    //   1534: lload 12
    //   1536: iload 14
    //   1538: invokevirtual 414	com/whatsapp/d/e:a	(JJZ)J
    //   1541: pop2
    //   1542: aload 15
    //   1544: astore 26
    //   1546: aload 16
    //   1548: astore 28
    //   1550: aload 21
    //   1552: astore 23
    //   1554: aload 15
    //   1556: astore 20
    //   1558: aload 16
    //   1560: astore 19
    //   1562: aload 17
    //   1564: astore 22
    //   1566: aload 15
    //   1568: astore 27
    //   1570: aload 16
    //   1572: astore 24
    //   1574: aload 15
    //   1576: astore 25
    //   1578: aload 16
    //   1580: astore 18
    //   1582: aload_0
    //   1583: getfield 227	com/whatsapp/m/e:n	Lcom/whatsapp/m/d;
    //   1586: invokevirtual 415	com/whatsapp/m/d:a	()Z
    //   1589: ifne -354 -> 1235
    //   1592: aload 15
    //   1594: astore 26
    //   1596: aload 16
    //   1598: astore 28
    //   1600: aload 21
    //   1602: astore 23
    //   1604: aload 15
    //   1606: astore 20
    //   1608: aload 16
    //   1610: astore 19
    //   1612: aload 17
    //   1614: astore 22
    //   1616: aload 15
    //   1618: astore 27
    //   1620: aload 16
    //   1622: astore 24
    //   1624: aload 15
    //   1626: astore 25
    //   1628: aload 16
    //   1630: astore 18
    //   1632: aload_0
    //   1633: getfield 227	com/whatsapp/m/e:n	Lcom/whatsapp/m/d;
    //   1636: aload 29
    //   1638: invokevirtual 416	com/whatsapp/m/b:a	()J
    //   1641: invokevirtual 419	com/whatsapp/m/d:a	(J)Z
    //   1644: ifne -409 -> 1235
    //   1647: aload 15
    //   1649: astore 26
    //   1651: aload 16
    //   1653: astore 28
    //   1655: aload 21
    //   1657: astore 23
    //   1659: aload 15
    //   1661: astore 20
    //   1663: aload 16
    //   1665: astore 19
    //   1667: aload 17
    //   1669: astore 22
    //   1671: aload 15
    //   1673: astore 27
    //   1675: aload 16
    //   1677: astore 24
    //   1679: aload 15
    //   1681: astore 25
    //   1683: aload 16
    //   1685: astore 18
    //   1687: aload_0
    //   1688: getfield 227	com/whatsapp/m/e:n	Lcom/whatsapp/m/d;
    //   1691: getfield 422	com/whatsapp/m/d:a	Lcom/whatsapp/m/d$a;
    //   1694: getstatic 425	com/whatsapp/m/d$a:a	Lcom/whatsapp/m/d$a;
    //   1697: if_acmpne +620 -> 2317
    //   1700: iconst_1
    //   1701: istore_2
    //   1702: iload_2
    //   1703: ifeq +619 -> 2322
    //   1706: aload 15
    //   1708: astore 26
    //   1710: aload 16
    //   1712: astore 28
    //   1714: aload 21
    //   1716: astore 23
    //   1718: aload 15
    //   1720: astore 20
    //   1722: aload 16
    //   1724: astore 19
    //   1726: aload 17
    //   1728: astore 22
    //   1730: aload 15
    //   1732: astore 27
    //   1734: aload 16
    //   1736: astore 24
    //   1738: aload 15
    //   1740: astore 25
    //   1742: aload 16
    //   1744: astore 18
    //   1746: aload_0
    //   1747: getfield 106	com/whatsapp/m/e:c	Lcom/whatsapp/fieldstats/events/au;
    //   1750: iload_3
    //   1751: i2l
    //   1752: invokestatic 277	java/lang/Long:valueOf	(J)Ljava/lang/Long;
    //   1755: putfield 427	com/whatsapp/fieldstats/events/au:h	Ljava/lang/Long;
    //   1758: goto -523 -> 1235
    //   1761: astore 19
    //   1763: aload 16
    //   1765: astore 18
    //   1767: aload 19
    //   1769: astore 16
    //   1771: aload_0
    //   1772: aload 16
    //   1774: putfield 429	com/whatsapp/m/e:d	Ljava/lang/Exception;
    //   1777: new 308	java/lang/StringBuilder
    //   1780: dup
    //   1781: ldc_w 431
    //   1784: invokespecial 311	java/lang/StringBuilder:<init>	(Ljava/lang/String;)V
    //   1787: aload_0
    //   1788: getfield 95	com/whatsapp/m/e:j	Ljava/net/URL;
    //   1791: invokestatic 436	com/whatsapp/util/MediaFileUtils:a	(Ljava/net/URL;)Ljava/lang/String;
    //   1794: invokevirtual 439	java/lang/StringBuilder:append	(Ljava/lang/String;)Ljava/lang/StringBuilder;
    //   1797: invokevirtual 321	java/lang/StringBuilder:toString	()Ljava/lang/String;
    //   1800: aload 16
    //   1802: invokestatic 442	com/whatsapp/util/Log:c	(Ljava/lang/String;Ljava/lang/Throwable;)V
    //   1805: getstatic 198	com/whatsapp/vk$d:a	Lcom/whatsapp/vk$d;
    //   1808: astore 16
    //   1810: aload 17
    //   1812: invokevirtual 298	java/io/RandomAccessFile:close	()V
    //   1815: aload 18
    //   1817: ifnull +8 -> 1825
    //   1820: aload 18
    //   1822: invokevirtual 299	java/io/InputStream:close	()V
    //   1825: aload 15
    //   1827: ifnull +8 -> 1835
    //   1830: aload 15
    //   1832: invokestatic 304	a/a/a/a/a/a$d:a	(Ljava/io/Closeable;)V
    //   1835: aload 21
    //   1837: invokevirtual 306	com/whatsapp/d/e:b	()V
    //   1840: aload 16
    //   1842: areturn
    //   1843: astore 16
    //   1845: ldc_w 444
    //   1848: invokestatic 196	com/whatsapp/util/Log:w	(Ljava/lang/String;)V
    //   1851: getstatic 446	com/whatsapp/vk$d:j	Lcom/whatsapp/vk$d;
    //   1854: astore 16
    //   1856: aload 15
    //   1858: ifnull +8 -> 1866
    //   1861: aload 15
    //   1863: invokestatic 304	a/a/a/a/a/a$d:a	(Ljava/io/Closeable;)V
    //   1866: aload 21
    //   1868: invokevirtual 306	com/whatsapp/d/e:b	()V
    //   1871: aload 16
    //   1873: areturn
    //   1874: astore 16
    //   1876: new 308	java/lang/StringBuilder
    //   1879: dup
    //   1880: ldc_w 448
    //   1883: invokespecial 311	java/lang/StringBuilder:<init>	(Ljava/lang/String;)V
    //   1886: lload 4
    //   1888: invokevirtual 317	java/lang/StringBuilder:append	(J)Ljava/lang/StringBuilder;
    //   1891: invokevirtual 321	java/lang/StringBuilder:toString	()Ljava/lang/String;
    //   1894: invokestatic 196	com/whatsapp/util/Log:w	(Ljava/lang/String;)V
    //   1897: getstatic 446	com/whatsapp/vk$d:j	Lcom/whatsapp/vk$d;
    //   1900: astore 16
    //   1902: aload 17
    //   1904: invokevirtual 298	java/io/RandomAccessFile:close	()V
    //   1907: aload 15
    //   1909: ifnull +8 -> 1917
    //   1912: aload 15
    //   1914: invokestatic 304	a/a/a/a/a/a$d:a	(Ljava/io/Closeable;)V
    //   1917: aload 21
    //   1919: invokevirtual 306	com/whatsapp/d/e:b	()V
    //   1922: aload 16
    //   1924: areturn
    //   1925: astore 17
    //   1927: ldc_w 450
    //   1930: aload 17
    //   1932: invokestatic 442	com/whatsapp/util/Log:c	(Ljava/lang/String;Ljava/lang/Throwable;)V
    //   1935: goto -28 -> 1907
    //   1938: iconst_0
    //   1939: istore_1
    //   1940: goto -1083 -> 857
    //   1943: astore 16
    //   1945: ldc_w 452
    //   1948: invokestatic 196	com/whatsapp/util/Log:w	(Ljava/lang/String;)V
    //   1951: getstatic 198	com/whatsapp/vk$d:a	Lcom/whatsapp/vk$d;
    //   1954: astore 16
    //   1956: aload 17
    //   1958: invokevirtual 298	java/io/RandomAccessFile:close	()V
    //   1961: aload 15
    //   1963: ifnull +8 -> 1971
    //   1966: aload 15
    //   1968: invokestatic 304	a/a/a/a/a/a$d:a	(Ljava/io/Closeable;)V
    //   1971: aload 21
    //   1973: invokevirtual 306	com/whatsapp/d/e:b	()V
    //   1976: aload 16
    //   1978: areturn
    //   1979: astore 17
    //   1981: ldc_w 450
    //   1984: aload 17
    //   1986: invokestatic 442	com/whatsapp/util/Log:c	(Ljava/lang/String;Ljava/lang/Throwable;)V
    //   1989: goto -28 -> 1961
    //   1992: iconst_0
    //   1993: istore 14
    //   1995: goto -500 -> 1495
    //   1998: astore 29
    //   2000: aload 15
    //   2002: astore 26
    //   2004: aload 16
    //   2006: astore 28
    //   2008: aload 21
    //   2010: astore 23
    //   2012: aload 15
    //   2014: astore 20
    //   2016: aload 16
    //   2018: astore 19
    //   2020: aload 17
    //   2022: astore 22
    //   2024: aload 15
    //   2026: astore 27
    //   2028: aload 16
    //   2030: astore 24
    //   2032: aload 15
    //   2034: astore 25
    //   2036: aload 16
    //   2038: astore 18
    //   2040: aload_0
    //   2041: getfield 106	com/whatsapp/m/e:c	Lcom/whatsapp/fieldstats/events/au;
    //   2044: iload_3
    //   2045: i2l
    //   2046: invokestatic 277	java/lang/Long:valueOf	(J)Ljava/lang/Long;
    //   2049: putfield 454	com/whatsapp/fieldstats/events/au:i	Ljava/lang/Long;
    //   2052: aload 15
    //   2054: astore 26
    //   2056: aload 16
    //   2058: astore 28
    //   2060: aload 21
    //   2062: astore 23
    //   2064: aload 15
    //   2066: astore 20
    //   2068: aload 16
    //   2070: astore 19
    //   2072: aload 17
    //   2074: astore 22
    //   2076: aload 15
    //   2078: astore 27
    //   2080: aload 16
    //   2082: astore 24
    //   2084: aload 15
    //   2086: astore 25
    //   2088: aload 16
    //   2090: astore 18
    //   2092: aload 29
    //   2094: athrow
    //   2095: astore 29
    //   2097: aload 15
    //   2099: astore 26
    //   2101: aload 16
    //   2103: astore 28
    //   2105: aload 21
    //   2107: astore 23
    //   2109: aload 15
    //   2111: astore 20
    //   2113: aload 16
    //   2115: astore 19
    //   2117: aload 17
    //   2119: astore 22
    //   2121: aload 15
    //   2123: astore 27
    //   2125: aload 16
    //   2127: astore 24
    //   2129: aload 15
    //   2131: astore 25
    //   2133: aload 16
    //   2135: astore 18
    //   2137: aload_0
    //   2138: aload 29
    //   2140: putfield 429	com/whatsapp/m/e:d	Ljava/lang/Exception;
    //   2143: aload 15
    //   2145: astore 26
    //   2147: aload 16
    //   2149: astore 28
    //   2151: aload 21
    //   2153: astore 23
    //   2155: aload 15
    //   2157: astore 20
    //   2159: aload 16
    //   2161: astore 19
    //   2163: aload 17
    //   2165: astore 22
    //   2167: aload 15
    //   2169: astore 27
    //   2171: aload 16
    //   2173: astore 24
    //   2175: aload 15
    //   2177: astore 25
    //   2179: aload 16
    //   2181: astore 18
    //   2183: ldc_w 456
    //   2186: invokestatic 196	com/whatsapp/util/Log:w	(Ljava/lang/String;)V
    //   2189: aload 15
    //   2191: astore 26
    //   2193: aload 16
    //   2195: astore 28
    //   2197: aload 21
    //   2199: astore 23
    //   2201: aload 15
    //   2203: astore 20
    //   2205: aload 16
    //   2207: astore 19
    //   2209: aload 17
    //   2211: astore 22
    //   2213: aload 15
    //   2215: astore 27
    //   2217: aload 16
    //   2219: astore 24
    //   2221: aload 15
    //   2223: astore 25
    //   2225: aload 16
    //   2227: astore 18
    //   2229: aload_0
    //   2230: getfield 66	com/whatsapp/m/e:i	Lcom/whatsapp/MediaData;
    //   2233: getstatic 459	com/whatsapp/MediaData:SUSPICIOUS_CONTENT_YES	I
    //   2236: putfield 462	com/whatsapp/MediaData:suspiciousContent	I
    //   2239: aload 15
    //   2241: astore 26
    //   2243: aload 16
    //   2245: astore 28
    //   2247: aload 21
    //   2249: astore 23
    //   2251: aload 15
    //   2253: astore 20
    //   2255: aload 16
    //   2257: astore 19
    //   2259: aload 17
    //   2261: astore 22
    //   2263: aload 15
    //   2265: astore 27
    //   2267: aload 16
    //   2269: astore 24
    //   2271: aload 15
    //   2273: astore 25
    //   2275: aload 16
    //   2277: astore 18
    //   2279: getstatic 198	com/whatsapp/vk$d:a	Lcom/whatsapp/vk$d;
    //   2282: astore 29
    //   2284: aload 17
    //   2286: invokevirtual 298	java/io/RandomAccessFile:close	()V
    //   2289: aload 16
    //   2291: ifnull +8 -> 2299
    //   2294: aload 16
    //   2296: invokevirtual 299	java/io/InputStream:close	()V
    //   2299: aload 15
    //   2301: ifnull +8 -> 2309
    //   2304: aload 15
    //   2306: invokestatic 304	a/a/a/a/a/a$d:a	(Ljava/io/Closeable;)V
    //   2309: aload 21
    //   2311: invokevirtual 306	com/whatsapp/d/e:b	()V
    //   2314: aload 29
    //   2316: areturn
    //   2317: iconst_0
    //   2318: istore_2
    //   2319: goto -617 -> 1702
    //   2322: aload 15
    //   2324: astore 26
    //   2326: aload 16
    //   2328: astore 28
    //   2330: aload 21
    //   2332: astore 23
    //   2334: aload 15
    //   2336: astore 20
    //   2338: aload 16
    //   2340: astore 19
    //   2342: aload 17
    //   2344: astore 22
    //   2346: aload 15
    //   2348: astore 27
    //   2350: aload 16
    //   2352: astore 24
    //   2354: aload 15
    //   2356: astore 25
    //   2358: aload 16
    //   2360: astore 18
    //   2362: aload_0
    //   2363: getfield 106	com/whatsapp/m/e:c	Lcom/whatsapp/fieldstats/events/au;
    //   2366: iconst_1
    //   2367: invokestatic 262	java/lang/Boolean:valueOf	(Z)Ljava/lang/Boolean;
    //   2370: putfield 464	com/whatsapp/fieldstats/events/au:g	Ljava/lang/Boolean;
    //   2373: aload 15
    //   2375: astore 26
    //   2377: aload 16
    //   2379: astore 28
    //   2381: aload 21
    //   2383: astore 23
    //   2385: aload 15
    //   2387: astore 20
    //   2389: aload 16
    //   2391: astore 19
    //   2393: aload 17
    //   2395: astore 22
    //   2397: aload 15
    //   2399: astore 27
    //   2401: aload 16
    //   2403: astore 24
    //   2405: aload 15
    //   2407: astore 25
    //   2409: aload 16
    //   2411: astore 18
    //   2413: new 9	com/whatsapp/m/e$b
    //   2416: dup
    //   2417: iconst_0
    //   2418: invokespecial 465	com/whatsapp/m/e$b:<init>	(B)V
    //   2421: athrow
    //   2422: aload 15
    //   2424: astore 26
    //   2426: aload 16
    //   2428: astore 28
    //   2430: aload 21
    //   2432: astore 23
    //   2434: aload 15
    //   2436: astore 20
    //   2438: aload 16
    //   2440: astore 19
    //   2442: aload 17
    //   2444: astore 22
    //   2446: aload 15
    //   2448: astore 27
    //   2450: aload 16
    //   2452: astore 24
    //   2454: aload 15
    //   2456: astore 25
    //   2458: aload 16
    //   2460: astore 18
    //   2462: aload 29
    //   2464: lload 6
    //   2466: iload_1
    //   2467: i2l
    //   2468: iconst_1
    //   2469: invokevirtual 381	com/whatsapp/m/b:a	(JJZ)Ljava/util/List;
    //   2472: pop
    //   2473: aload 15
    //   2475: astore 26
    //   2477: aload 16
    //   2479: astore 28
    //   2481: aload 21
    //   2483: astore 23
    //   2485: aload 15
    //   2487: astore 20
    //   2489: aload 16
    //   2491: astore 19
    //   2493: aload 17
    //   2495: astore 22
    //   2497: aload 15
    //   2499: astore 27
    //   2501: aload 16
    //   2503: astore 24
    //   2505: aload 15
    //   2507: astore 25
    //   2509: aload 16
    //   2511: astore 18
    //   2513: aload 30
    //   2515: invokeinterface 386 1 0
    //   2520: ifne +52 -> 2572
    //   2523: aload 15
    //   2525: astore 26
    //   2527: aload 16
    //   2529: astore 28
    //   2531: aload 21
    //   2533: astore 23
    //   2535: aload 15
    //   2537: astore 20
    //   2539: aload 16
    //   2541: astore 19
    //   2543: aload 17
    //   2545: astore 22
    //   2547: aload 15
    //   2549: astore 27
    //   2551: aload 16
    //   2553: astore 24
    //   2555: aload 15
    //   2557: astore 25
    //   2559: aload 16
    //   2561: astore 18
    //   2563: aload 29
    //   2565: aload_0
    //   2566: getfield 101	com/whatsapp/m/e:m	Ljava/io/File;
    //   2569: invokevirtual 468	com/whatsapp/m/b:a	(Ljava/io/File;)V
    //   2572: iload_1
    //   2573: i2l
    //   2574: lload 4
    //   2576: ladd
    //   2577: lstore 8
    //   2579: lload 6
    //   2581: iload_1
    //   2582: i2l
    //   2583: ladd
    //   2584: lstore 6
    //   2586: aload 15
    //   2588: astore 26
    //   2590: aload 16
    //   2592: astore 28
    //   2594: aload 21
    //   2596: astore 23
    //   2598: aload 15
    //   2600: astore 20
    //   2602: aload 16
    //   2604: astore 19
    //   2606: aload 17
    //   2608: astore 22
    //   2610: aload 15
    //   2612: astore 27
    //   2614: aload 16
    //   2616: astore 24
    //   2618: aload 15
    //   2620: astore 25
    //   2622: aload 16
    //   2624: astore 18
    //   2626: aload_0
    //   2627: getfield 93	com/whatsapp/m/e:a	Lcom/whatsapp/m/a;
    //   2630: getstatic 470	com/whatsapp/m/a$a:c	Lcom/whatsapp/m/a$a;
    //   2633: invokevirtual 245	com/whatsapp/m/a:a	(Lcom/whatsapp/m/a$a;)V
    //   2636: aload 15
    //   2638: astore 26
    //   2640: aload 16
    //   2642: astore 28
    //   2644: aload 21
    //   2646: astore 23
    //   2648: aload 15
    //   2650: astore 20
    //   2652: aload 16
    //   2654: astore 19
    //   2656: aload 17
    //   2658: astore 22
    //   2660: aload 15
    //   2662: astore 27
    //   2664: aload 16
    //   2666: astore 24
    //   2668: aload 15
    //   2670: astore 25
    //   2672: aload 16
    //   2674: astore 18
    //   2676: aload_0
    //   2677: getfield 91	com/whatsapp/m/e:g	Lcom/whatsapp/vk;
    //   2680: invokevirtual 473	com/whatsapp/vk:isCancelled	()Z
    //   2683: ifeq +202 -> 2885
    //   2686: aload 15
    //   2688: astore 26
    //   2690: aload 16
    //   2692: astore 28
    //   2694: aload 21
    //   2696: astore 23
    //   2698: aload 15
    //   2700: astore 20
    //   2702: aload 16
    //   2704: astore 19
    //   2706: aload 17
    //   2708: astore 22
    //   2710: aload 15
    //   2712: astore 27
    //   2714: aload 16
    //   2716: astore 24
    //   2718: aload 15
    //   2720: astore 25
    //   2722: aload 16
    //   2724: astore 18
    //   2726: ldc_w 475
    //   2729: invokestatic 186	com/whatsapp/util/Log:i	(Ljava/lang/String;)V
    //   2732: aload 15
    //   2734: astore 26
    //   2736: aload 16
    //   2738: astore 28
    //   2740: aload 21
    //   2742: astore 23
    //   2744: aload 15
    //   2746: astore 20
    //   2748: aload 16
    //   2750: astore 19
    //   2752: aload 17
    //   2754: astore 22
    //   2756: aload 15
    //   2758: astore 27
    //   2760: aload 16
    //   2762: astore 24
    //   2764: aload 15
    //   2766: astore 25
    //   2768: aload 16
    //   2770: astore 18
    //   2772: aload 29
    //   2774: aload_0
    //   2775: getfield 101	com/whatsapp/m/e:m	Ljava/io/File;
    //   2778: invokevirtual 468	com/whatsapp/m/b:a	(Ljava/io/File;)V
    //   2781: aload 15
    //   2783: astore 26
    //   2785: aload 16
    //   2787: astore 28
    //   2789: aload 21
    //   2791: astore 23
    //   2793: aload 15
    //   2795: astore 20
    //   2797: aload 16
    //   2799: astore 19
    //   2801: aload 17
    //   2803: astore 22
    //   2805: aload 15
    //   2807: astore 27
    //   2809: aload 16
    //   2811: astore 24
    //   2813: aload 15
    //   2815: astore 25
    //   2817: aload 16
    //   2819: astore 18
    //   2821: getstatic 191	com/whatsapp/vk$d:l	Lcom/whatsapp/vk$d;
    //   2824: astore 29
    //   2826: aload 17
    //   2828: invokevirtual 298	java/io/RandomAccessFile:close	()V
    //   2831: aload 16
    //   2833: ifnull +8 -> 2841
    //   2836: aload 16
    //   2838: invokevirtual 299	java/io/InputStream:close	()V
    //   2841: aload 15
    //   2843: ifnull +8 -> 2851
    //   2846: aload 15
    //   2848: invokestatic 304	a/a/a/a/a/a$d:a	(Ljava/io/Closeable;)V
    //   2851: aload 21
    //   2853: invokevirtual 306	com/whatsapp/d/e:b	()V
    //   2856: aload 29
    //   2858: areturn
    //   2859: astore 17
    //   2861: ldc_w 450
    //   2864: aload 17
    //   2866: invokestatic 442	com/whatsapp/util/Log:c	(Ljava/lang/String;Ljava/lang/Throwable;)V
    //   2869: goto -38 -> 2831
    //   2872: astore 16
    //   2874: ldc_w 477
    //   2877: aload 16
    //   2879: invokestatic 442	com/whatsapp/util/Log:c	(Ljava/lang/String;Ljava/lang/Throwable;)V
    //   2882: goto -41 -> 2841
    //   2885: aload 15
    //   2887: astore 26
    //   2889: aload 16
    //   2891: astore 28
    //   2893: aload 21
    //   2895: astore 23
    //   2897: aload 15
    //   2899: astore 20
    //   2901: aload 16
    //   2903: astore 19
    //   2905: aload 17
    //   2907: astore 22
    //   2909: aload 15
    //   2911: astore 27
    //   2913: aload 16
    //   2915: astore 24
    //   2917: aload 15
    //   2919: astore 25
    //   2921: aload 16
    //   2923: astore 18
    //   2925: aload_0
    //   2926: getfield 93	com/whatsapp/m/e:a	Lcom/whatsapp/m/a;
    //   2929: getfield 480	com/whatsapp/m/a:a	Lcom/whatsapp/m/c;
    //   2932: invokevirtual 483	com/whatsapp/m/c:a	()Z
    //   2935: ifeq +2777 -> 5712
    //   2938: aload 15
    //   2940: astore 26
    //   2942: aload 16
    //   2944: astore 28
    //   2946: aload 21
    //   2948: astore 23
    //   2950: aload 15
    //   2952: astore 20
    //   2954: aload 16
    //   2956: astore 19
    //   2958: aload 17
    //   2960: astore 22
    //   2962: aload 15
    //   2964: astore 27
    //   2966: aload 16
    //   2968: astore 24
    //   2970: aload 15
    //   2972: astore 25
    //   2974: aload 16
    //   2976: astore 18
    //   2978: aload_0
    //   2979: getfield 227	com/whatsapp/m/e:n	Lcom/whatsapp/m/d;
    //   2982: invokevirtual 415	com/whatsapp/m/d:a	()Z
    //   2985: ifeq +2727 -> 5712
    //   2988: aload 15
    //   2990: astore 26
    //   2992: aload 16
    //   2994: astore 28
    //   2996: aload 21
    //   2998: astore 23
    //   3000: aload 15
    //   3002: astore 20
    //   3004: aload 16
    //   3006: astore 19
    //   3008: aload 17
    //   3010: astore 22
    //   3012: aload 15
    //   3014: astore 27
    //   3016: aload 16
    //   3018: astore 24
    //   3020: aload 15
    //   3022: astore 25
    //   3024: aload 16
    //   3026: astore 18
    //   3028: aload_0
    //   3029: getfield 93	com/whatsapp/m/e:a	Lcom/whatsapp/m/a;
    //   3032: getfield 480	com/whatsapp/m/a:a	Lcom/whatsapp/m/c;
    //   3035: invokevirtual 484	com/whatsapp/m/c:b	()J
    //   3038: lstore 4
    //   3040: aload 15
    //   3042: astore 26
    //   3044: aload 16
    //   3046: astore 28
    //   3048: aload 21
    //   3050: astore 23
    //   3052: aload 15
    //   3054: astore 20
    //   3056: aload 16
    //   3058: astore 19
    //   3060: aload 17
    //   3062: astore 22
    //   3064: aload 15
    //   3066: astore 27
    //   3068: aload 16
    //   3070: astore 24
    //   3072: aload 15
    //   3074: astore 25
    //   3076: aload 16
    //   3078: astore 18
    //   3080: new 308	java/lang/StringBuilder
    //   3083: dup
    //   3084: ldc_w 486
    //   3087: invokespecial 311	java/lang/StringBuilder:<init>	(Ljava/lang/String;)V
    //   3090: lload 4
    //   3092: invokevirtual 317	java/lang/StringBuilder:append	(J)Ljava/lang/StringBuilder;
    //   3095: invokevirtual 321	java/lang/StringBuilder:toString	()Ljava/lang/String;
    //   3098: invokestatic 488	com/whatsapp/util/Log:d	(Ljava/lang/String;)V
    //   3101: aload 15
    //   3103: astore 26
    //   3105: aload 16
    //   3107: astore 28
    //   3109: aload 21
    //   3111: astore 23
    //   3113: aload 15
    //   3115: astore 20
    //   3117: aload 16
    //   3119: astore 19
    //   3121: aload 17
    //   3123: astore 22
    //   3125: aload 15
    //   3127: astore 27
    //   3129: aload 16
    //   3131: astore 24
    //   3133: aload 15
    //   3135: astore 25
    //   3137: aload 16
    //   3139: astore 18
    //   3141: aload 29
    //   3143: lload 4
    //   3145: invokevirtual 327	com/whatsapp/m/b:a	(J)J
    //   3148: lstore 10
    //   3150: lload 10
    //   3152: lload 6
    //   3154: lcmp
    //   3155: ifne +633 -> 3788
    //   3158: aload 15
    //   3160: astore 26
    //   3162: aload 16
    //   3164: astore 28
    //   3166: aload 21
    //   3168: astore 23
    //   3170: aload 15
    //   3172: astore 20
    //   3174: aload 16
    //   3176: astore 19
    //   3178: aload 17
    //   3180: astore 22
    //   3182: aload 15
    //   3184: astore 27
    //   3186: aload 16
    //   3188: astore 24
    //   3190: aload 15
    //   3192: astore 25
    //   3194: aload 16
    //   3196: astore 18
    //   3198: ldc_w 490
    //   3201: invokestatic 488	com/whatsapp/util/Log:d	(Ljava/lang/String;)V
    //   3204: goto +2508 -> 5712
    //   3207: lload 6
    //   3209: lload 4
    //   3211: lcmp
    //   3212: ifeq +729 -> 3941
    //   3215: aload 15
    //   3217: astore 26
    //   3219: aload 16
    //   3221: astore 28
    //   3223: aload 21
    //   3225: astore 23
    //   3227: aload 15
    //   3229: astore 20
    //   3231: aload 16
    //   3233: astore 19
    //   3235: aload 17
    //   3237: astore 22
    //   3239: aload 15
    //   3241: astore 27
    //   3243: aload 16
    //   3245: astore 24
    //   3247: aload 15
    //   3249: astore 25
    //   3251: aload 16
    //   3253: astore 18
    //   3255: aload_0
    //   3256: getfield 106	com/whatsapp/m/e:c	Lcom/whatsapp/fieldstats/events/au;
    //   3259: astore 30
    //   3261: aload 15
    //   3263: astore 26
    //   3265: aload 16
    //   3267: astore 28
    //   3269: aload 21
    //   3271: astore 23
    //   3273: aload 15
    //   3275: astore 20
    //   3277: aload 16
    //   3279: astore 19
    //   3281: aload 17
    //   3283: astore 22
    //   3285: aload 15
    //   3287: astore 27
    //   3289: aload 16
    //   3291: astore 24
    //   3293: aload 15
    //   3295: astore 25
    //   3297: aload 16
    //   3299: astore 18
    //   3301: aload 30
    //   3303: aload 30
    //   3305: getfield 492	com/whatsapp/fieldstats/events/au:f	Ljava/lang/Long;
    //   3308: invokevirtual 495	java/lang/Long:longValue	()J
    //   3311: lconst_1
    //   3312: ladd
    //   3313: invokestatic 277	java/lang/Long:valueOf	(J)Ljava/lang/Long;
    //   3316: putfield 492	com/whatsapp/fieldstats/events/au:f	Ljava/lang/Long;
    //   3319: aload 15
    //   3321: astore 26
    //   3323: aload 16
    //   3325: astore 28
    //   3327: aload 21
    //   3329: astore 23
    //   3331: aload 15
    //   3333: astore 20
    //   3335: aload 16
    //   3337: astore 19
    //   3339: aload 17
    //   3341: astore 22
    //   3343: aload 15
    //   3345: astore 27
    //   3347: aload 16
    //   3349: astore 24
    //   3351: aload 15
    //   3353: astore 25
    //   3355: aload 16
    //   3357: astore 18
    //   3359: aload 29
    //   3361: aload_0
    //   3362: getfield 101	com/whatsapp/m/e:m	Ljava/io/File;
    //   3365: invokevirtual 468	com/whatsapp/m/b:a	(Ljava/io/File;)V
    //   3368: lload 4
    //   3370: lstore 6
    //   3372: lload 8
    //   3374: lstore 4
    //   3376: aload 15
    //   3378: astore 26
    //   3380: aload 16
    //   3382: astore 28
    //   3384: aload 21
    //   3386: astore 23
    //   3388: aload 15
    //   3390: astore 20
    //   3392: aload 16
    //   3394: astore 19
    //   3396: aload 17
    //   3398: astore 22
    //   3400: aload 15
    //   3402: astore 27
    //   3404: aload 16
    //   3406: astore 24
    //   3408: aload 15
    //   3410: astore 25
    //   3412: aload 16
    //   3414: astore 18
    //   3416: aload 29
    //   3418: lload 6
    //   3420: invokevirtual 327	com/whatsapp/m/b:a	(J)J
    //   3423: lstore 8
    //   3425: lload 8
    //   3427: lload 6
    //   3429: lcmp
    //   3430: ifeq +2257 -> 5687
    //   3433: lload 8
    //   3435: lstore 6
    //   3437: lload 8
    //   3439: lconst_0
    //   3440: lcmp
    //   3441: ifge +2278 -> 5719
    //   3444: aload 15
    //   3446: astore 26
    //   3448: aload 16
    //   3450: astore 28
    //   3452: aload 21
    //   3454: astore 23
    //   3456: aload 15
    //   3458: astore 20
    //   3460: aload 16
    //   3462: astore 19
    //   3464: aload 17
    //   3466: astore 22
    //   3468: aload 15
    //   3470: astore 27
    //   3472: aload 16
    //   3474: astore 24
    //   3476: aload 15
    //   3478: astore 25
    //   3480: aload 16
    //   3482: astore 18
    //   3484: aload 29
    //   3486: lconst_0
    //   3487: invokevirtual 327	com/whatsapp/m/b:a	(J)J
    //   3490: lstore 6
    //   3492: lload 6
    //   3494: lconst_0
    //   3495: lcmp
    //   3496: iflt +866 -> 4362
    //   3499: goto +2220 -> 5719
    //   3502: aload 15
    //   3504: astore 26
    //   3506: aload 16
    //   3508: astore 28
    //   3510: aload 21
    //   3512: astore 23
    //   3514: aload 15
    //   3516: astore 20
    //   3518: aload 16
    //   3520: astore 19
    //   3522: aload 17
    //   3524: astore 22
    //   3526: aload 15
    //   3528: astore 27
    //   3530: aload 16
    //   3532: astore 24
    //   3534: aload 15
    //   3536: astore 25
    //   3538: aload 16
    //   3540: astore 18
    //   3542: aload 29
    //   3544: lload 6
    //   3546: invokevirtual 333	com/whatsapp/m/b:c	(J)J
    //   3549: lstore 10
    //   3551: aload 15
    //   3553: astore 26
    //   3555: aload 16
    //   3557: astore 28
    //   3559: aload 21
    //   3561: astore 23
    //   3563: aload 15
    //   3565: astore 20
    //   3567: aload 16
    //   3569: astore 19
    //   3571: aload 17
    //   3573: astore 22
    //   3575: aload 15
    //   3577: astore 27
    //   3579: aload 16
    //   3581: astore 24
    //   3583: aload 15
    //   3585: astore 25
    //   3587: aload 16
    //   3589: astore 18
    //   3591: aload 15
    //   3593: getfield 352	com/whatsapp/i/a$a:a	Ljavax/net/ssl/HttpsURLConnection;
    //   3596: invokevirtual 499	javax/net/ssl/HttpsURLConnection:getURL	()Ljava/net/URL;
    //   3599: astore 30
    //   3601: aload 15
    //   3603: astore 26
    //   3605: aload 16
    //   3607: astore 28
    //   3609: aload 21
    //   3611: astore 23
    //   3613: aload 15
    //   3615: astore 20
    //   3617: aload 16
    //   3619: astore 19
    //   3621: aload 17
    //   3623: astore 22
    //   3625: aload 15
    //   3627: astore 27
    //   3629: aload 16
    //   3631: astore 24
    //   3633: aload 15
    //   3635: astore 25
    //   3637: aload 16
    //   3639: astore 18
    //   3641: aload 15
    //   3643: invokestatic 304	a/a/a/a/a/a$d:a	(Ljava/io/Closeable;)V
    //   3646: aload 15
    //   3648: astore 26
    //   3650: aload 16
    //   3652: astore 28
    //   3654: aload 21
    //   3656: astore 23
    //   3658: aload 15
    //   3660: astore 20
    //   3662: aload 16
    //   3664: astore 19
    //   3666: aload 17
    //   3668: astore 22
    //   3670: aload 15
    //   3672: astore 27
    //   3674: aload 16
    //   3676: astore 24
    //   3678: aload 15
    //   3680: astore 25
    //   3682: aload 16
    //   3684: astore 18
    //   3686: aload_0
    //   3687: aload 30
    //   3689: lload 8
    //   3691: lload 10
    //   3693: invokespecial 249	com/whatsapp/m/e:a	(Ljava/net/URL;JJ)Lcom/whatsapp/i/a$a;
    //   3696: astore 30
    //   3698: aload 30
    //   3700: astore 15
    //   3702: aload 15
    //   3704: getfield 352	com/whatsapp/i/a$a:a	Ljavax/net/ssl/HttpsURLConnection;
    //   3707: invokevirtual 358	javax/net/ssl/HttpsURLConnection:getInputStream	()Ljava/io/InputStream;
    //   3710: astore 18
    //   3712: aload_0
    //   3713: getfield 59	com/whatsapp/m/e:h	Lcom/whatsapp/protocol/j;
    //   3716: invokevirtual 360	com/whatsapp/protocol/j:a	()Z
    //   3719: ifeq +549 -> 4268
    //   3722: iconst_4
    //   3723: istore_1
    //   3724: new 362	com/whatsapp/Statistics$a
    //   3727: dup
    //   3728: aload 18
    //   3730: iload_1
    //   3731: invokespecial 365	com/whatsapp/Statistics$a:<init>	(Ljava/io/InputStream;I)V
    //   3734: astore 18
    //   3736: lload 6
    //   3738: ldc2_w 500
    //   3741: lcmp
    //   3742: ifle +605 -> 4347
    //   3745: aload 18
    //   3747: invokestatic 503	com/whatsapp/m/e:a	(Ljava/io/InputStream;)[B
    //   3750: astore 16
    //   3752: aload 17
    //   3754: lload 6
    //   3756: ldc2_w 500
    //   3759: lsub
    //   3760: invokevirtual 349	java/io/RandomAccessFile:seek	(J)V
    //   3763: aload 17
    //   3765: aload 16
    //   3767: iconst_0
    //   3768: bipush 16
    //   3770: invokevirtual 369	java/io/RandomAccessFile:write	([BII)V
    //   3773: aload 17
    //   3775: invokevirtual 373	java/io/RandomAccessFile:getFD	()Ljava/io/FileDescriptor;
    //   3778: invokevirtual 378	java/io/FileDescriptor:sync	()V
    //   3781: aload 18
    //   3783: astore 16
    //   3785: goto -2861 -> 924
    //   3788: aload 15
    //   3790: astore 26
    //   3792: aload 16
    //   3794: astore 28
    //   3796: aload 21
    //   3798: astore 23
    //   3800: aload 15
    //   3802: astore 20
    //   3804: aload 16
    //   3806: astore 19
    //   3808: aload 17
    //   3810: astore 22
    //   3812: aload 15
    //   3814: astore 27
    //   3816: aload 16
    //   3818: astore 24
    //   3820: aload 15
    //   3822: astore 25
    //   3824: aload 16
    //   3826: astore 18
    //   3828: new 308	java/lang/StringBuilder
    //   3831: dup
    //   3832: ldc_w 505
    //   3835: invokespecial 311	java/lang/StringBuilder:<init>	(Ljava/lang/String;)V
    //   3838: lload 6
    //   3840: invokevirtual 317	java/lang/StringBuilder:append	(J)Ljava/lang/StringBuilder;
    //   3843: ldc_w 507
    //   3846: invokevirtual 439	java/lang/StringBuilder:append	(Ljava/lang/String;)Ljava/lang/StringBuilder;
    //   3849: lload 10
    //   3851: invokevirtual 317	java/lang/StringBuilder:append	(J)Ljava/lang/StringBuilder;
    //   3854: invokevirtual 321	java/lang/StringBuilder:toString	()Ljava/lang/String;
    //   3857: invokestatic 186	com/whatsapp/util/Log:i	(Ljava/lang/String;)V
    //   3860: goto -653 -> 3207
    //   3863: astore 15
    //   3865: aload 28
    //   3867: astore 16
    //   3869: aload 26
    //   3871: astore 15
    //   3873: aload 21
    //   3875: astore 23
    //   3877: aload 15
    //   3879: astore 20
    //   3881: aload 16
    //   3883: astore 19
    //   3885: aload 17
    //   3887: astore 22
    //   3889: getstatic 509	com/whatsapp/vk$d:h	Lcom/whatsapp/vk$d;
    //   3892: astore 18
    //   3894: aload 17
    //   3896: ifnull +8 -> 3904
    //   3899: aload 17
    //   3901: invokevirtual 298	java/io/RandomAccessFile:close	()V
    //   3904: aload 16
    //   3906: ifnull +8 -> 3914
    //   3909: aload 16
    //   3911: invokevirtual 299	java/io/InputStream:close	()V
    //   3914: aload 15
    //   3916: ifnull +8 -> 3924
    //   3919: aload 15
    //   3921: invokestatic 304	a/a/a/a/a/a$d:a	(Ljava/io/Closeable;)V
    //   3924: aload 18
    //   3926: astore 16
    //   3928: aload 21
    //   3930: ifnull -3857 -> 73
    //   3933: aload 21
    //   3935: invokevirtual 306	com/whatsapp/d/e:b	()V
    //   3938: aload 18
    //   3940: areturn
    //   3941: aload 15
    //   3943: astore 26
    //   3945: aload 16
    //   3947: astore 28
    //   3949: aload 21
    //   3951: astore 23
    //   3953: aload 15
    //   3955: astore 20
    //   3957: aload 16
    //   3959: astore 19
    //   3961: aload 17
    //   3963: astore 22
    //   3965: aload 15
    //   3967: astore 27
    //   3969: aload 16
    //   3971: astore 24
    //   3973: aload 15
    //   3975: astore 25
    //   3977: aload 16
    //   3979: astore 18
    //   3981: aload_0
    //   3982: getfield 93	com/whatsapp/m/e:a	Lcom/whatsapp/m/a;
    //   3985: lload 8
    //   3987: invokevirtual 331	com/whatsapp/m/a:b	(J)V
    //   3990: aload 15
    //   3992: astore 26
    //   3994: aload 16
    //   3996: astore 28
    //   3998: aload 21
    //   4000: astore 23
    //   4002: aload 15
    //   4004: astore 20
    //   4006: aload 16
    //   4008: astore 19
    //   4010: aload 17
    //   4012: astore 22
    //   4014: aload 15
    //   4016: astore 27
    //   4018: aload 16
    //   4020: astore 24
    //   4022: aload 15
    //   4024: astore 25
    //   4026: aload 16
    //   4028: astore 18
    //   4030: aload_0
    //   4031: getfield 91	com/whatsapp/m/e:g	Lcom/whatsapp/vk;
    //   4034: getfield 171	com/whatsapp/vk:f	Lcom/whatsapp/vk$a;
    //   4037: getstatic 200	com/whatsapp/vk$a:c	Lcom/whatsapp/vk$a;
    //   4040: if_acmpne +162 -> 4202
    //   4043: lload 8
    //   4045: ldc2_w 336
    //   4048: lcmp
    //   4049: iflt +153 -> 4202
    //   4052: aload 15
    //   4054: astore 26
    //   4056: aload 16
    //   4058: astore 28
    //   4060: aload 21
    //   4062: astore 23
    //   4064: aload 15
    //   4066: astore 20
    //   4068: aload 16
    //   4070: astore 19
    //   4072: aload 17
    //   4074: astore 22
    //   4076: aload 15
    //   4078: astore 27
    //   4080: aload 16
    //   4082: astore 24
    //   4084: aload 15
    //   4086: astore 25
    //   4088: aload 16
    //   4090: astore 18
    //   4092: ldc_w 339
    //   4095: invokestatic 186	com/whatsapp/util/Log:i	(Ljava/lang/String;)V
    //   4098: aload 15
    //   4100: astore 26
    //   4102: aload 16
    //   4104: astore 28
    //   4106: aload 21
    //   4108: astore 23
    //   4110: aload 15
    //   4112: astore 20
    //   4114: aload 16
    //   4116: astore 19
    //   4118: aload 17
    //   4120: astore 22
    //   4122: aload 15
    //   4124: astore 27
    //   4126: aload 16
    //   4128: astore 24
    //   4130: aload 15
    //   4132: astore 25
    //   4134: aload 16
    //   4136: astore 18
    //   4138: getstatic 215	com/whatsapp/vk$d:m	Lcom/whatsapp/vk$d;
    //   4141: astore 29
    //   4143: aload 17
    //   4145: invokevirtual 298	java/io/RandomAccessFile:close	()V
    //   4148: aload 16
    //   4150: ifnull +8 -> 4158
    //   4153: aload 16
    //   4155: invokevirtual 299	java/io/InputStream:close	()V
    //   4158: aload 15
    //   4160: ifnull +8 -> 4168
    //   4163: aload 15
    //   4165: invokestatic 304	a/a/a/a/a/a$d:a	(Ljava/io/Closeable;)V
    //   4168: aload 21
    //   4170: invokevirtual 306	com/whatsapp/d/e:b	()V
    //   4173: aload 29
    //   4175: areturn
    //   4176: astore 17
    //   4178: ldc_w 450
    //   4181: aload 17
    //   4183: invokestatic 442	com/whatsapp/util/Log:c	(Ljava/lang/String;Ljava/lang/Throwable;)V
    //   4186: goto -38 -> 4148
    //   4189: astore 16
    //   4191: ldc_w 477
    //   4194: aload 16
    //   4196: invokestatic 442	com/whatsapp/util/Log:c	(Ljava/lang/String;Ljava/lang/Throwable;)V
    //   4199: goto -41 -> 4158
    //   4202: aload 15
    //   4204: astore 26
    //   4206: aload 16
    //   4208: astore 28
    //   4210: aload 21
    //   4212: astore 23
    //   4214: aload 15
    //   4216: astore 20
    //   4218: aload 16
    //   4220: astore 19
    //   4222: aload 17
    //   4224: astore 22
    //   4226: aload 15
    //   4228: astore 27
    //   4230: aload 16
    //   4232: astore 24
    //   4234: aload 15
    //   4236: astore 25
    //   4238: aload 16
    //   4240: astore 18
    //   4242: aload 16
    //   4244: aload 31
    //   4246: iconst_0
    //   4247: sipush 8192
    //   4250: invokevirtual 145	java/io/InputStream:read	([BII)I
    //   4253: istore_1
    //   4254: lload 8
    //   4256: lstore 4
    //   4258: goto -3275 -> 983
    //   4261: lload 6
    //   4263: lstore 8
    //   4265: goto -763 -> 3502
    //   4268: iconst_0
    //   4269: istore_1
    //   4270: goto -546 -> 3724
    //   4273: astore 18
    //   4275: ldc_w 452
    //   4278: aload 18
    //   4280: invokestatic 442	com/whatsapp/util/Log:c	(Ljava/lang/String;Ljava/lang/Throwable;)V
    //   4283: getstatic 198	com/whatsapp/vk$d:a	Lcom/whatsapp/vk$d;
    //   4286: astore 18
    //   4288: aload 17
    //   4290: invokevirtual 298	java/io/RandomAccessFile:close	()V
    //   4293: aload 16
    //   4295: ifnull +8 -> 4303
    //   4298: aload 16
    //   4300: invokevirtual 299	java/io/InputStream:close	()V
    //   4303: aload 15
    //   4305: ifnull +8 -> 4313
    //   4308: aload 15
    //   4310: invokestatic 304	a/a/a/a/a/a$d:a	(Ljava/io/Closeable;)V
    //   4313: aload 21
    //   4315: invokevirtual 306	com/whatsapp/d/e:b	()V
    //   4318: aload 18
    //   4320: areturn
    //   4321: astore 17
    //   4323: ldc_w 450
    //   4326: aload 17
    //   4328: invokestatic 442	com/whatsapp/util/Log:c	(Ljava/lang/String;Ljava/lang/Throwable;)V
    //   4331: goto -38 -> 4293
    //   4334: astore 16
    //   4336: ldc_w 477
    //   4339: aload 16
    //   4341: invokestatic 442	com/whatsapp/util/Log:c	(Ljava/lang/String;Ljava/lang/Throwable;)V
    //   4344: goto -41 -> 4303
    //   4347: aload 17
    //   4349: lload 6
    //   4351: invokevirtual 349	java/io/RandomAccessFile:seek	(J)V
    //   4354: goto -573 -> 3781
    //   4357: astore 16
    //   4359: goto -2588 -> 1771
    //   4362: aload 15
    //   4364: astore 26
    //   4366: aload 16
    //   4368: astore 28
    //   4370: aload 21
    //   4372: astore 23
    //   4374: aload 15
    //   4376: astore 20
    //   4378: aload 16
    //   4380: astore 19
    //   4382: aload 17
    //   4384: astore 22
    //   4386: aload 15
    //   4388: astore 27
    //   4390: aload 16
    //   4392: astore 24
    //   4394: aload 15
    //   4396: astore 25
    //   4398: aload 16
    //   4400: astore 18
    //   4402: aload_0
    //   4403: getfield 93	com/whatsapp/m/e:a	Lcom/whatsapp/m/a;
    //   4406: getstatic 511	com/whatsapp/m/a$a:d	Lcom/whatsapp/m/a$a;
    //   4409: invokevirtual 245	com/whatsapp/m/a:a	(Lcom/whatsapp/m/a$a;)V
    //   4412: aload 15
    //   4414: astore 26
    //   4416: aload 16
    //   4418: astore 28
    //   4420: aload 21
    //   4422: astore 23
    //   4424: aload 15
    //   4426: astore 20
    //   4428: aload 16
    //   4430: astore 19
    //   4432: aload 17
    //   4434: astore 22
    //   4436: aload 15
    //   4438: astore 27
    //   4440: aload 16
    //   4442: astore 24
    //   4444: aload 15
    //   4446: astore 25
    //   4448: aload 16
    //   4450: astore 18
    //   4452: ldc_w 513
    //   4455: invokestatic 186	com/whatsapp/util/Log:i	(Ljava/lang/String;)V
    //   4458: aload 15
    //   4460: astore 26
    //   4462: aload 16
    //   4464: astore 28
    //   4466: aload 21
    //   4468: astore 23
    //   4470: aload 15
    //   4472: astore 20
    //   4474: aload 16
    //   4476: astore 19
    //   4478: aload 17
    //   4480: astore 22
    //   4482: aload 15
    //   4484: astore 27
    //   4486: aload 16
    //   4488: astore 24
    //   4490: aload 15
    //   4492: astore 25
    //   4494: aload 16
    //   4496: astore 18
    //   4498: aload 21
    //   4500: invokevirtual 515	com/whatsapp/d/e:a	()V
    //   4503: aload 17
    //   4505: invokevirtual 298	java/io/RandomAccessFile:close	()V
    //   4508: aload 16
    //   4510: ifnull +8 -> 4518
    //   4513: aload 16
    //   4515: invokevirtual 299	java/io/InputStream:close	()V
    //   4518: aload 15
    //   4520: ifnull +8 -> 4528
    //   4523: aload 15
    //   4525: invokestatic 304	a/a/a/a/a/a$d:a	(Ljava/io/Closeable;)V
    //   4528: aload 21
    //   4530: invokevirtual 306	com/whatsapp/d/e:b	()V
    //   4533: ldc_w 517
    //   4536: invokestatic 186	com/whatsapp/util/Log:i	(Ljava/lang/String;)V
    //   4539: getstatic 519	com/whatsapp/vk$d:d	Lcom/whatsapp/vk$d;
    //   4542: areturn
    //   4543: astore 29
    //   4545: aload 15
    //   4547: astore 26
    //   4549: aload 16
    //   4551: astore 28
    //   4553: aload 21
    //   4555: astore 23
    //   4557: aload 15
    //   4559: astore 20
    //   4561: aload 16
    //   4563: astore 19
    //   4565: aload 17
    //   4567: astore 22
    //   4569: aload 15
    //   4571: astore 27
    //   4573: aload 16
    //   4575: astore 24
    //   4577: aload 15
    //   4579: astore 25
    //   4581: aload 16
    //   4583: astore 18
    //   4585: aload_0
    //   4586: getfield 91	com/whatsapp/m/e:g	Lcom/whatsapp/vk;
    //   4589: invokevirtual 473	com/whatsapp/vk:isCancelled	()Z
    //   4592: ifeq +153 -> 4745
    //   4595: aload 15
    //   4597: astore 26
    //   4599: aload 16
    //   4601: astore 28
    //   4603: aload 21
    //   4605: astore 23
    //   4607: aload 15
    //   4609: astore 20
    //   4611: aload 16
    //   4613: astore 19
    //   4615: aload 17
    //   4617: astore 22
    //   4619: aload 15
    //   4621: astore 27
    //   4623: aload 16
    //   4625: astore 24
    //   4627: aload 15
    //   4629: astore 25
    //   4631: aload 16
    //   4633: astore 18
    //   4635: ldc_w 521
    //   4638: invokestatic 196	com/whatsapp/util/Log:w	(Ljava/lang/String;)V
    //   4641: aload 15
    //   4643: astore 26
    //   4645: aload 16
    //   4647: astore 28
    //   4649: aload 21
    //   4651: astore 23
    //   4653: aload 15
    //   4655: astore 20
    //   4657: aload 16
    //   4659: astore 19
    //   4661: aload 17
    //   4663: astore 22
    //   4665: aload 15
    //   4667: astore 27
    //   4669: aload 16
    //   4671: astore 24
    //   4673: aload 15
    //   4675: astore 25
    //   4677: aload 16
    //   4679: astore 18
    //   4681: getstatic 191	com/whatsapp/vk$d:l	Lcom/whatsapp/vk$d;
    //   4684: astore 29
    //   4686: aload 17
    //   4688: invokevirtual 298	java/io/RandomAccessFile:close	()V
    //   4691: aload 16
    //   4693: ifnull +8 -> 4701
    //   4696: aload 16
    //   4698: invokevirtual 299	java/io/InputStream:close	()V
    //   4701: aload 15
    //   4703: ifnull +8 -> 4711
    //   4706: aload 15
    //   4708: invokestatic 304	a/a/a/a/a/a$d:a	(Ljava/io/Closeable;)V
    //   4711: aload 21
    //   4713: invokevirtual 306	com/whatsapp/d/e:b	()V
    //   4716: aload 29
    //   4718: areturn
    //   4719: astore 17
    //   4721: ldc_w 450
    //   4724: aload 17
    //   4726: invokestatic 442	com/whatsapp/util/Log:c	(Ljava/lang/String;Ljava/lang/Throwable;)V
    //   4729: goto -38 -> 4691
    //   4732: astore 16
    //   4734: ldc_w 477
    //   4737: aload 16
    //   4739: invokestatic 442	com/whatsapp/util/Log:c	(Ljava/lang/String;Ljava/lang/Throwable;)V
    //   4742: goto -41 -> 4701
    //   4745: aload 15
    //   4747: astore 26
    //   4749: aload 16
    //   4751: astore 28
    //   4753: aload 21
    //   4755: astore 23
    //   4757: aload 15
    //   4759: astore 20
    //   4761: aload 16
    //   4763: astore 19
    //   4765: aload 17
    //   4767: astore 22
    //   4769: aload 15
    //   4771: astore 27
    //   4773: aload 16
    //   4775: astore 24
    //   4777: aload 15
    //   4779: astore 25
    //   4781: aload 16
    //   4783: astore 18
    //   4785: new 308	java/lang/StringBuilder
    //   4788: dup
    //   4789: ldc_w 523
    //   4792: invokespecial 311	java/lang/StringBuilder:<init>	(Ljava/lang/String;)V
    //   4795: aload_0
    //   4796: getfield 95	com/whatsapp/m/e:j	Ljava/net/URL;
    //   4799: invokestatic 436	com/whatsapp/util/MediaFileUtils:a	(Ljava/net/URL;)Ljava/lang/String;
    //   4802: invokevirtual 439	java/lang/StringBuilder:append	(Ljava/lang/String;)Ljava/lang/StringBuilder;
    //   4805: invokevirtual 321	java/lang/StringBuilder:toString	()Ljava/lang/String;
    //   4808: aload 29
    //   4810: invokestatic 442	com/whatsapp/util/Log:c	(Ljava/lang/String;Ljava/lang/Throwable;)V
    //   4813: aload 15
    //   4815: astore 26
    //   4817: aload 16
    //   4819: astore 28
    //   4821: aload 21
    //   4823: astore 23
    //   4825: aload 15
    //   4827: astore 20
    //   4829: aload 16
    //   4831: astore 19
    //   4833: aload 17
    //   4835: astore 22
    //   4837: aload 15
    //   4839: astore 27
    //   4841: aload 16
    //   4843: astore 24
    //   4845: aload 15
    //   4847: astore 25
    //   4849: aload 16
    //   4851: astore 18
    //   4853: getstatic 509	com/whatsapp/vk$d:h	Lcom/whatsapp/vk$d;
    //   4856: astore 29
    //   4858: aload 17
    //   4860: invokevirtual 298	java/io/RandomAccessFile:close	()V
    //   4863: aload 16
    //   4865: ifnull +8 -> 4873
    //   4868: aload 16
    //   4870: invokevirtual 299	java/io/InputStream:close	()V
    //   4873: aload 15
    //   4875: ifnull +8 -> 4883
    //   4878: aload 15
    //   4880: invokestatic 304	a/a/a/a/a/a$d:a	(Ljava/io/Closeable;)V
    //   4883: aload 21
    //   4885: invokevirtual 306	com/whatsapp/d/e:b	()V
    //   4888: aload 29
    //   4890: areturn
    //   4891: astore 17
    //   4893: ldc_w 450
    //   4896: aload 17
    //   4898: invokestatic 442	com/whatsapp/util/Log:c	(Ljava/lang/String;Ljava/lang/Throwable;)V
    //   4901: goto -38 -> 4863
    //   4904: astore 16
    //   4906: ldc_w 477
    //   4909: aload 16
    //   4911: invokestatic 442	com/whatsapp/util/Log:c	(Ljava/lang/String;Ljava/lang/Throwable;)V
    //   4914: goto -41 -> 4873
    //   4917: astore 17
    //   4919: ldc_w 450
    //   4922: aload 17
    //   4924: invokestatic 442	com/whatsapp/util/Log:c	(Ljava/lang/String;Ljava/lang/Throwable;)V
    //   4927: goto -3112 -> 1815
    //   4930: astore 17
    //   4932: ldc_w 477
    //   4935: aload 17
    //   4937: invokestatic 442	com/whatsapp/util/Log:c	(Ljava/lang/String;Ljava/lang/Throwable;)V
    //   4940: goto -3115 -> 1825
    //   4943: astore 17
    //   4945: ldc_w 450
    //   4948: aload 17
    //   4950: invokestatic 442	com/whatsapp/util/Log:c	(Ljava/lang/String;Ljava/lang/Throwable;)V
    //   4953: goto -2664 -> 2289
    //   4956: astore 16
    //   4958: ldc_w 477
    //   4961: aload 16
    //   4963: invokestatic 442	com/whatsapp/util/Log:c	(Ljava/lang/String;Ljava/lang/Throwable;)V
    //   4966: goto -2667 -> 2299
    //   4969: astore 17
    //   4971: ldc_w 450
    //   4974: aload 17
    //   4976: invokestatic 442	com/whatsapp/util/Log:c	(Ljava/lang/String;Ljava/lang/Throwable;)V
    //   4979: goto -471 -> 4508
    //   4982: astore 16
    //   4984: ldc_w 477
    //   4987: aload 16
    //   4989: invokestatic 442	com/whatsapp/util/Log:c	(Ljava/lang/String;Ljava/lang/Throwable;)V
    //   4992: goto -474 -> 4518
    //   4995: astore 17
    //   4997: ldc_w 450
    //   5000: aload 17
    //   5002: invokestatic 442	com/whatsapp/util/Log:c	(Ljava/lang/String;Ljava/lang/Throwable;)V
    //   5005: goto -4522 -> 483
    //   5008: astore 16
    //   5010: ldc_w 477
    //   5013: aload 16
    //   5015: invokestatic 442	com/whatsapp/util/Log:c	(Ljava/lang/String;Ljava/lang/Throwable;)V
    //   5018: goto -4525 -> 493
    //   5021: astore 17
    //   5023: ldc_w 450
    //   5026: aload 17
    //   5028: invokestatic 442	com/whatsapp/util/Log:c	(Ljava/lang/String;Ljava/lang/Throwable;)V
    //   5031: goto -1127 -> 3904
    //   5034: astore 16
    //   5036: ldc_w 477
    //   5039: aload 16
    //   5041: invokestatic 442	com/whatsapp/util/Log:c	(Ljava/lang/String;Ljava/lang/Throwable;)V
    //   5044: goto -1130 -> 3914
    //   5047: astore 18
    //   5049: aconst_null
    //   5050: astore 21
    //   5052: aconst_null
    //   5053: astore 15
    //   5055: aconst_null
    //   5056: astore 16
    //   5058: aconst_null
    //   5059: astore 17
    //   5061: aload 21
    //   5063: astore 23
    //   5065: aload 15
    //   5067: astore 20
    //   5069: aload 16
    //   5071: astore 19
    //   5073: aload 17
    //   5075: astore 22
    //   5077: aload_0
    //   5078: aload 18
    //   5080: putfield 429	com/whatsapp/m/e:d	Ljava/lang/Exception;
    //   5083: aload 21
    //   5085: astore 23
    //   5087: aload 15
    //   5089: astore 20
    //   5091: aload 16
    //   5093: astore 19
    //   5095: aload 17
    //   5097: astore 22
    //   5099: new 308	java/lang/StringBuilder
    //   5102: dup
    //   5103: ldc_w 525
    //   5106: invokespecial 311	java/lang/StringBuilder:<init>	(Ljava/lang/String;)V
    //   5109: aload 18
    //   5111: getfield 529	com/whatsapp/MediaDownloadConnection$ConnectionFailureException:message	Ljava/lang/String;
    //   5114: invokevirtual 439	java/lang/StringBuilder:append	(Ljava/lang/String;)Ljava/lang/StringBuilder;
    //   5117: ldc_w 531
    //   5120: invokevirtual 439	java/lang/StringBuilder:append	(Ljava/lang/String;)Ljava/lang/StringBuilder;
    //   5123: aload_0
    //   5124: getfield 59	com/whatsapp/m/e:h	Lcom/whatsapp/protocol/j;
    //   5127: getfield 534	com/whatsapp/protocol/j:e	Lcom/whatsapp/protocol/j$b;
    //   5130: invokevirtual 537	java/lang/StringBuilder:append	(Ljava/lang/Object;)Ljava/lang/StringBuilder;
    //   5133: ldc_w 539
    //   5136: invokevirtual 439	java/lang/StringBuilder:append	(Ljava/lang/String;)Ljava/lang/StringBuilder;
    //   5139: aload_0
    //   5140: getfield 95	com/whatsapp/m/e:j	Ljava/net/URL;
    //   5143: invokestatic 436	com/whatsapp/util/MediaFileUtils:a	(Ljava/net/URL;)Ljava/lang/String;
    //   5146: invokevirtual 439	java/lang/StringBuilder:append	(Ljava/lang/String;)Ljava/lang/StringBuilder;
    //   5149: invokevirtual 321	java/lang/StringBuilder:toString	()Ljava/lang/String;
    //   5152: invokestatic 186	com/whatsapp/util/Log:i	(Ljava/lang/String;)V
    //   5155: aload 21
    //   5157: astore 23
    //   5159: aload 15
    //   5161: astore 20
    //   5163: aload 16
    //   5165: astore 19
    //   5167: aload 17
    //   5169: astore 22
    //   5171: aload 18
    //   5173: getfield 542	com/whatsapp/MediaDownloadConnection$ConnectionFailureException:code	Lcom/whatsapp/vk$d;
    //   5176: astore 18
    //   5178: aload 17
    //   5180: ifnull +8 -> 5188
    //   5183: aload 17
    //   5185: invokevirtual 298	java/io/RandomAccessFile:close	()V
    //   5188: aload 16
    //   5190: ifnull +8 -> 5198
    //   5193: aload 16
    //   5195: invokevirtual 299	java/io/InputStream:close	()V
    //   5198: aload 15
    //   5200: ifnull +8 -> 5208
    //   5203: aload 15
    //   5205: invokestatic 304	a/a/a/a/a/a$d:a	(Ljava/io/Closeable;)V
    //   5208: aload 18
    //   5210: astore 16
    //   5212: aload 21
    //   5214: ifnull -5141 -> 73
    //   5217: aload 21
    //   5219: invokevirtual 306	com/whatsapp/d/e:b	()V
    //   5222: aload 18
    //   5224: areturn
    //   5225: astore 17
    //   5227: ldc_w 450
    //   5230: aload 17
    //   5232: invokestatic 442	com/whatsapp/util/Log:c	(Ljava/lang/String;Ljava/lang/Throwable;)V
    //   5235: goto -47 -> 5188
    //   5238: astore 16
    //   5240: ldc_w 477
    //   5243: aload 16
    //   5245: invokestatic 442	com/whatsapp/util/Log:c	(Ljava/lang/String;Ljava/lang/Throwable;)V
    //   5248: goto -50 -> 5198
    //   5251: astore 18
    //   5253: aconst_null
    //   5254: astore 21
    //   5256: aconst_null
    //   5257: astore 15
    //   5259: aconst_null
    //   5260: astore 16
    //   5262: aconst_null
    //   5263: astore 17
    //   5265: aload 17
    //   5267: ifnull +8 -> 5275
    //   5270: aload 17
    //   5272: invokevirtual 298	java/io/RandomAccessFile:close	()V
    //   5275: aload 16
    //   5277: ifnull +8 -> 5285
    //   5280: aload 16
    //   5282: invokevirtual 299	java/io/InputStream:close	()V
    //   5285: aload 15
    //   5287: ifnull +8 -> 5295
    //   5290: aload 15
    //   5292: invokestatic 304	a/a/a/a/a/a$d:a	(Ljava/io/Closeable;)V
    //   5295: aload 21
    //   5297: ifnull +8 -> 5305
    //   5300: aload 21
    //   5302: invokevirtual 306	com/whatsapp/d/e:b	()V
    //   5305: aload 18
    //   5307: athrow
    //   5308: astore 17
    //   5310: ldc_w 450
    //   5313: aload 17
    //   5315: invokestatic 442	com/whatsapp/util/Log:c	(Ljava/lang/String;Ljava/lang/Throwable;)V
    //   5318: goto -43 -> 5275
    //   5321: astore 16
    //   5323: ldc_w 477
    //   5326: aload 16
    //   5328: invokestatic 442	com/whatsapp/util/Log:c	(Ljava/lang/String;Ljava/lang/Throwable;)V
    //   5331: goto -46 -> 5285
    //   5334: astore 18
    //   5336: aconst_null
    //   5337: astore 21
    //   5339: aconst_null
    //   5340: astore 17
    //   5342: aconst_null
    //   5343: astore 19
    //   5345: aload 16
    //   5347: astore 15
    //   5349: aload 19
    //   5351: astore 16
    //   5353: goto -88 -> 5265
    //   5356: astore 18
    //   5358: aconst_null
    //   5359: astore 16
    //   5361: aconst_null
    //   5362: astore 17
    //   5364: goto -99 -> 5265
    //   5367: astore 18
    //   5369: aconst_null
    //   5370: astore 16
    //   5372: goto -107 -> 5265
    //   5375: astore 18
    //   5377: aload 23
    //   5379: astore 21
    //   5381: aload 20
    //   5383: astore 15
    //   5385: aload 19
    //   5387: astore 16
    //   5389: aload 22
    //   5391: astore 17
    //   5393: goto -128 -> 5265
    //   5396: astore 18
    //   5398: goto -133 -> 5265
    //   5401: astore 19
    //   5403: aload 18
    //   5405: astore 16
    //   5407: aload 19
    //   5409: astore 18
    //   5411: goto -146 -> 5265
    //   5414: astore 19
    //   5416: aload 18
    //   5418: astore 16
    //   5420: aload 19
    //   5422: astore 18
    //   5424: goto -159 -> 5265
    //   5427: astore 18
    //   5429: goto -164 -> 5265
    //   5432: astore 18
    //   5434: aconst_null
    //   5435: astore 21
    //   5437: aconst_null
    //   5438: astore 19
    //   5440: aconst_null
    //   5441: astore 16
    //   5443: aload 17
    //   5445: astore 15
    //   5447: aload 19
    //   5449: astore 17
    //   5451: goto -390 -> 5061
    //   5454: astore 18
    //   5456: aconst_null
    //   5457: astore 16
    //   5459: aconst_null
    //   5460: astore 17
    //   5462: goto -401 -> 5061
    //   5465: astore 18
    //   5467: aconst_null
    //   5468: astore 16
    //   5470: goto -409 -> 5061
    //   5473: astore 18
    //   5475: aload 27
    //   5477: astore 15
    //   5479: aload 24
    //   5481: astore 16
    //   5483: goto -422 -> 5061
    //   5486: astore 18
    //   5488: goto -427 -> 5061
    //   5491: astore 19
    //   5493: aload 18
    //   5495: astore 16
    //   5497: aload 19
    //   5499: astore 18
    //   5501: goto -440 -> 5061
    //   5504: astore 19
    //   5506: aload 18
    //   5508: astore 16
    //   5510: aload 19
    //   5512: astore 18
    //   5514: goto -453 -> 5061
    //   5517: astore 15
    //   5519: aconst_null
    //   5520: astore 21
    //   5522: aconst_null
    //   5523: astore 15
    //   5525: aconst_null
    //   5526: astore 16
    //   5528: aconst_null
    //   5529: astore 17
    //   5531: goto -1658 -> 3873
    //   5534: astore 15
    //   5536: aconst_null
    //   5537: astore 21
    //   5539: aconst_null
    //   5540: astore 17
    //   5542: aconst_null
    //   5543: astore 16
    //   5545: aload 19
    //   5547: astore 15
    //   5549: goto -1676 -> 3873
    //   5552: astore 16
    //   5554: aconst_null
    //   5555: astore 16
    //   5557: aconst_null
    //   5558: astore 17
    //   5560: goto -1687 -> 3873
    //   5563: astore 16
    //   5565: aconst_null
    //   5566: astore 16
    //   5568: goto -1695 -> 3873
    //   5571: astore 18
    //   5573: goto -1700 -> 3873
    //   5576: astore 16
    //   5578: aload 18
    //   5580: astore 16
    //   5582: goto -1709 -> 3873
    //   5585: astore 16
    //   5587: aload 18
    //   5589: astore 16
    //   5591: goto -1718 -> 3873
    //   5594: astore 15
    //   5596: aconst_null
    //   5597: astore 21
    //   5599: aconst_null
    //   5600: astore 15
    //   5602: aconst_null
    //   5603: astore 17
    //   5605: aconst_null
    //   5606: astore 16
    //   5608: goto -5140 -> 468
    //   5611: astore 15
    //   5613: aconst_null
    //   5614: astore 21
    //   5616: aconst_null
    //   5617: astore 17
    //   5619: aconst_null
    //   5620: astore 16
    //   5622: aload 18
    //   5624: astore 15
    //   5626: goto -5158 -> 468
    //   5629: astore 16
    //   5631: aconst_null
    //   5632: astore 16
    //   5634: goto -5166 -> 468
    //   5637: astore 18
    //   5639: goto -5171 -> 468
    //   5642: astore 16
    //   5644: aload 18
    //   5646: astore 16
    //   5648: goto -5180 -> 468
    //   5651: astore 16
    //   5653: aload 18
    //   5655: astore 16
    //   5657: goto -5189 -> 468
    //   5660: astore 29
    //   5662: goto -3565 -> 2097
    //   5665: astore 29
    //   5667: aload 18
    //   5669: astore 16
    //   5671: goto -3574 -> 2097
    //   5674: astore 19
    //   5676: aload 16
    //   5678: astore 18
    //   5680: aload 19
    //   5682: astore 16
    //   5684: goto -3913 -> 1771
    //   5687: goto -4763 -> 924
    //   5690: goto -2314 -> 3376
    //   5693: aconst_null
    //   5694: astore 16
    //   5696: goto -4827 -> 869
    //   5699: astore 15
    //   5701: aload 25
    //   5703: astore 15
    //   5705: aload 18
    //   5707: astore 16
    //   5709: goto -5241 -> 468
    //   5712: lload 6
    //   5714: lstore 4
    //   5716: goto -2509 -> 3207
    //   5719: lload 6
    //   5721: ldc2_w 500
    //   5724: lcmp
    //   5725: ifle -1464 -> 4261
    //   5728: lload 6
    //   5730: ldc2_w 500
    //   5733: lsub
    //   5734: lstore 8
    //   5736: goto -2234 -> 3502
    // Local variable table:
    //   start	length	slot	name	signature
    //   0	5739	0	this	e
    //   856	3414	1	i1	int
    //   1484	835	2	i2	int
    //   1338	707	3	i3	int
    //   170	5545	4	l1	long
    //   266	5463	6	l2	long
    //   740	4995	8	l3	long
    //   1388	2462	10	l4	long
    //   1437	98	12	l5	long
    //   1493	501	14	bool	boolean
    //   76	1	15	localIOException1	IOException
    //   104	3717	15	localObject1	Object
    //   3863	1	15	locala1	com.whatsapp.d.e.a
    //   3871	1607	15	localObject2	Object
    //   5517	1	15	locala2	com.whatsapp.d.e.a
    //   5523	1	15	localObject3	Object
    //   5534	1	15	locala3	com.whatsapp.d.e.a
    //   5547	1	15	localObject4	Object
    //   5594	1	15	locala4	a
    //   5600	1	15	localObject5	Object
    //   5611	1	15	locala5	a
    //   5624	1	15	localObject6	Object
    //   5699	1	15	locala6	a
    //   5703	1	15	localObject7	Object
    //   71	309	16	localObject8	Object
    //   460	1	16	locala7	a
    //   463	162	16	localObject9	Object
    //   673	1	16	localIOException2	IOException
    //   677	1164	16	localObject10	Object
    //   1843	1	16	localFileNotFoundException	java.io.FileNotFoundException
    //   1854	18	16	locald1	com.whatsapp.vk.d
    //   1874	1	16	localIOException3	IOException
    //   1900	23	16	locald2	com.whatsapp.vk.d
    //   1943	1	16	localIOException4	IOException
    //   1954	883	16	locald3	com.whatsapp.vk.d
    //   2872	811	16	localIOException5	IOException
    //   3750	404	16	localObject11	Object
    //   4189	110	16	localIOException6	IOException
    //   4334	6	16	localIOException7	IOException
    //   4357	340	16	localIOException8	IOException
    //   4732	137	16	localIOException9	IOException
    //   4904	6	16	localIOException10	IOException
    //   4956	6	16	localIOException11	IOException
    //   4982	6	16	localIOException12	IOException
    //   5008	6	16	localIOException13	IOException
    //   5034	6	16	localIOException14	IOException
    //   5056	155	16	localObject12	Object
    //   5238	6	16	localIOException15	IOException
    //   5260	21	16	localObject13	Object
    //   5321	25	16	localIOException16	IOException
    //   5351	193	16	localObject14	Object
    //   5552	1	16	locala8	com.whatsapp.d.e.a
    //   5555	1	16	localObject15	Object
    //   5563	1	16	locala9	com.whatsapp.d.e.a
    //   5566	1	16	localObject16	Object
    //   5576	1	16	locala10	com.whatsapp.d.e.a
    //   5580	1	16	localObject17	Object
    //   5585	1	16	locala11	com.whatsapp.d.e.a
    //   5589	32	16	localObject18	Object
    //   5629	1	16	locala12	a
    //   5632	1	16	localObject19	Object
    //   5642	1	16	locala13	a
    //   5646	1	16	localObject20	Object
    //   5651	1	16	locala14	a
    //   5655	53	16	localObject21	Object
    //   251	1652	17	localObject22	Object
    //   1925	32	17	localIOException17	IOException
    //   1979	848	17	localIOException18	IOException
    //   2859	1285	17	localIOException19	IOException
    //   4176	113	17	localIOException20	IOException
    //   4321	366	17	localIOException21	IOException
    //   4719	140	17	localIOException22	IOException
    //   4891	6	17	localIOException23	IOException
    //   4917	6	17	localIOException24	IOException
    //   4930	6	17	localIOException25	IOException
    //   4943	6	17	localIOException26	IOException
    //   4969	6	17	localIOException27	IOException
    //   4995	6	17	localIOException28	IOException
    //   5021	6	17	localIOException29	IOException
    //   5059	125	17	localObject23	Object
    //   5225	6	17	localIOException30	IOException
    //   5263	8	17	localObject24	Object
    //   5308	6	17	localIOException31	IOException
    //   5340	278	17	localObject25	Object
    //   259	3982	18	localObject26	Object
    //   4273	6	18	localIOException32	IOException
    //   4286	566	18	localObject27	Object
    //   5047	125	18	localConnectionFailureException1	com.whatsapp.MediaDownloadConnection.ConnectionFailureException
    //   5176	47	18	locald4	com.whatsapp.vk.d
    //   5251	55	18	localObject28	Object
    //   5334	1	18	localObject29	Object
    //   5356	1	18	localObject30	Object
    //   5367	1	18	localObject31	Object
    //   5375	1	18	localObject32	Object
    //   5396	8	18	localObject33	Object
    //   5409	14	18	localObject34	Object
    //   5427	1	18	localObject35	Object
    //   5432	1	18	localConnectionFailureException2	com.whatsapp.MediaDownloadConnection.ConnectionFailureException
    //   5454	1	18	localConnectionFailureException3	com.whatsapp.MediaDownloadConnection.ConnectionFailureException
    //   5465	1	18	localConnectionFailureException4	com.whatsapp.MediaDownloadConnection.ConnectionFailureException
    //   5473	1	18	localConnectionFailureException5	com.whatsapp.MediaDownloadConnection.ConnectionFailureException
    //   5486	8	18	localConnectionFailureException6	com.whatsapp.MediaDownloadConnection.ConnectionFailureException
    //   5499	14	18	localConnectionFailureException7	com.whatsapp.MediaDownloadConnection.ConnectionFailureException
    //   5571	52	18	locala15	com.whatsapp.d.e.a
    //   5637	31	18	locala16	a
    //   5678	28	18	localObject36	Object
    //   255	1470	19	localObject37	Object
    //   1761	7	19	localIOException33	IOException
    //   2018	3368	19	localObject38	Object
    //   5401	7	19	localObject39	Object
    //   5414	7	19	localObject40	Object
    //   5438	10	19	localObject41	Object
    //   5491	7	19	localConnectionFailureException8	com.whatsapp.MediaDownloadConnection.ConnectionFailureException
    //   5504	42	19	localConnectionFailureException9	com.whatsapp.MediaDownloadConnection.ConnectionFailureException
    //   5674	7	19	localIOException34	IOException
    //   174	5208	20	localObject42	Object
    //   418	5197	21	localObject43	Object
    //   891	4499	22	localObject44	Object
    //   879	4499	23	localObject45	Object
    //   899	4581	24	localObject46	Object
    //   903	4799	25	localObject47	Object
    //   871	3945	26	localObject48	Object
    //   895	4581	27	localObject49	Object
    //   875	3945	28	localObject50	Object
    //   293	1344	29	localObject51	Object
    //   1998	95	29	locala17	com.whatsapp.d.e.a
    //   2095	44	29	localb1	b
    //   2282	1892	29	locald5	com.whatsapp.vk.d
    //   4543	1	29	localIOException35	IOException
    //   4684	205	29	locald6	com.whatsapp.vk.d
    //   5660	1	29	localb2	b
    //   5665	1	29	localb3	b
    //   1134	2565	30	localObject52	Object
    //   914	3331	31	arrayOfByte	byte[]
    //   1233	93	32	localIterator	java.util.Iterator
    // Exception table:
    //   from	to	target	type
    //   0	18	76	java/io/IOException
    //   18	36	76	java/io/IOException
    //   420	460	460	com/whatsapp/m/e$a
    //   735	755	460	com/whatsapp/m/e$a
    //   764	775	460	com/whatsapp/m/e$a
    //   793	805	460	com/whatsapp/m/e$a
    //   805	821	460	com/whatsapp/m/e$a
    //   1845	1856	460	com/whatsapp/m/e$a
    //   393	420	673	java/io/IOException
    //   971	983	1761	java/io/IOException
    //   1027	1036	1761	java/io/IOException
    //   1076	1084	1761	java/io/IOException
    //   1124	1136	1761	java/io/IOException
    //   1176	1186	1761	java/io/IOException
    //   1226	1235	1761	java/io/IOException
    //   1275	1285	1761	java/io/IOException
    //   1325	1339	1761	java/io/IOException
    //   1383	1390	1761	java/io/IOException
    //   1430	1439	1761	java/io/IOException
    //   1479	1485	1761	java/io/IOException
    //   1527	1542	1761	java/io/IOException
    //   1582	1592	1761	java/io/IOException
    //   1632	1647	1761	java/io/IOException
    //   1687	1700	1761	java/io/IOException
    //   1746	1758	1761	java/io/IOException
    //   2040	2052	1761	java/io/IOException
    //   2092	2095	1761	java/io/IOException
    //   2362	2373	1761	java/io/IOException
    //   2413	2422	1761	java/io/IOException
    //   2462	2473	1761	java/io/IOException
    //   2513	2523	1761	java/io/IOException
    //   2563	2572	1761	java/io/IOException
    //   2626	2636	1761	java/io/IOException
    //   2676	2686	1761	java/io/IOException
    //   2726	2732	1761	java/io/IOException
    //   2772	2781	1761	java/io/IOException
    //   2821	2826	1761	java/io/IOException
    //   2925	2938	1761	java/io/IOException
    //   2978	2988	1761	java/io/IOException
    //   3028	3040	1761	java/io/IOException
    //   3080	3101	1761	java/io/IOException
    //   3141	3150	1761	java/io/IOException
    //   3198	3204	1761	java/io/IOException
    //   3255	3261	1761	java/io/IOException
    //   3301	3319	1761	java/io/IOException
    //   3359	3368	1761	java/io/IOException
    //   3416	3425	1761	java/io/IOException
    //   3484	3492	1761	java/io/IOException
    //   3542	3551	1761	java/io/IOException
    //   3591	3601	1761	java/io/IOException
    //   3641	3646	1761	java/io/IOException
    //   3686	3698	1761	java/io/IOException
    //   3828	3860	1761	java/io/IOException
    //   3981	3990	1761	java/io/IOException
    //   4030	4043	1761	java/io/IOException
    //   4092	4098	1761	java/io/IOException
    //   4138	4143	1761	java/io/IOException
    //   4242	4254	1761	java/io/IOException
    //   4402	4412	1761	java/io/IOException
    //   4585	4595	1761	java/io/IOException
    //   4635	4641	1761	java/io/IOException
    //   4681	4686	1761	java/io/IOException
    //   4785	4813	1761	java/io/IOException
    //   4853	4858	1761	java/io/IOException
    //   805	821	1843	java/io/FileNotFoundException
    //   828	835	1874	java/io/IOException
    //   1902	1907	1925	java/io/IOException
    //   835	855	1943	java/io/IOException
    //   857	869	1943	java/io/IOException
    //   1956	1961	1979	java/io/IOException
    //   1527	1542	1998	com/whatsapp/d/e$a
    //   971	983	2095	com/whatsapp/m/e$b
    //   1027	1036	2095	com/whatsapp/m/e$b
    //   1076	1084	2095	com/whatsapp/m/e$b
    //   1124	1136	2095	com/whatsapp/m/e$b
    //   1176	1186	2095	com/whatsapp/m/e$b
    //   1226	1235	2095	com/whatsapp/m/e$b
    //   1275	1285	2095	com/whatsapp/m/e$b
    //   1325	1339	2095	com/whatsapp/m/e$b
    //   1383	1390	2095	com/whatsapp/m/e$b
    //   1430	1439	2095	com/whatsapp/m/e$b
    //   1479	1485	2095	com/whatsapp/m/e$b
    //   1527	1542	2095	com/whatsapp/m/e$b
    //   1582	1592	2095	com/whatsapp/m/e$b
    //   1632	1647	2095	com/whatsapp/m/e$b
    //   1687	1700	2095	com/whatsapp/m/e$b
    //   1746	1758	2095	com/whatsapp/m/e$b
    //   2040	2052	2095	com/whatsapp/m/e$b
    //   2092	2095	2095	com/whatsapp/m/e$b
    //   2362	2373	2095	com/whatsapp/m/e$b
    //   2413	2422	2095	com/whatsapp/m/e$b
    //   2462	2473	2095	com/whatsapp/m/e$b
    //   2513	2523	2095	com/whatsapp/m/e$b
    //   2563	2572	2095	com/whatsapp/m/e$b
    //   2626	2636	2095	com/whatsapp/m/e$b
    //   2676	2686	2095	com/whatsapp/m/e$b
    //   2726	2732	2095	com/whatsapp/m/e$b
    //   2772	2781	2095	com/whatsapp/m/e$b
    //   2821	2826	2095	com/whatsapp/m/e$b
    //   2925	2938	2095	com/whatsapp/m/e$b
    //   2978	2988	2095	com/whatsapp/m/e$b
    //   3028	3040	2095	com/whatsapp/m/e$b
    //   3080	3101	2095	com/whatsapp/m/e$b
    //   3141	3150	2095	com/whatsapp/m/e$b
    //   3198	3204	2095	com/whatsapp/m/e$b
    //   3255	3261	2095	com/whatsapp/m/e$b
    //   3301	3319	2095	com/whatsapp/m/e$b
    //   3359	3368	2095	com/whatsapp/m/e$b
    //   3416	3425	2095	com/whatsapp/m/e$b
    //   3484	3492	2095	com/whatsapp/m/e$b
    //   3542	3551	2095	com/whatsapp/m/e$b
    //   3591	3601	2095	com/whatsapp/m/e$b
    //   3641	3646	2095	com/whatsapp/m/e$b
    //   3686	3698	2095	com/whatsapp/m/e$b
    //   3828	3860	2095	com/whatsapp/m/e$b
    //   3981	3990	2095	com/whatsapp/m/e$b
    //   4030	4043	2095	com/whatsapp/m/e$b
    //   4092	4098	2095	com/whatsapp/m/e$b
    //   4138	4143	2095	com/whatsapp/m/e$b
    //   4242	4254	2095	com/whatsapp/m/e$b
    //   4402	4412	2095	com/whatsapp/m/e$b
    //   4452	4458	2095	com/whatsapp/m/e$b
    //   4498	4503	2095	com/whatsapp/m/e$b
    //   4585	4595	2095	com/whatsapp/m/e$b
    //   4635	4641	2095	com/whatsapp/m/e$b
    //   4681	4686	2095	com/whatsapp/m/e$b
    //   4785	4813	2095	com/whatsapp/m/e$b
    //   4853	4858	2095	com/whatsapp/m/e$b
    //   2826	2831	2859	java/io/IOException
    //   2836	2841	2872	java/io/IOException
    //   909	916	3863	com/whatsapp/d/e$a
    //   971	983	3863	com/whatsapp/d/e$a
    //   1027	1036	3863	com/whatsapp/d/e$a
    //   1076	1084	3863	com/whatsapp/d/e$a
    //   1124	1136	3863	com/whatsapp/d/e$a
    //   1176	1186	3863	com/whatsapp/d/e$a
    //   1226	1235	3863	com/whatsapp/d/e$a
    //   1275	1285	3863	com/whatsapp/d/e$a
    //   1325	1339	3863	com/whatsapp/d/e$a
    //   1383	1390	3863	com/whatsapp/d/e$a
    //   1430	1439	3863	com/whatsapp/d/e$a
    //   1479	1485	3863	com/whatsapp/d/e$a
    //   1582	1592	3863	com/whatsapp/d/e$a
    //   1632	1647	3863	com/whatsapp/d/e$a
    //   1687	1700	3863	com/whatsapp/d/e$a
    //   1746	1758	3863	com/whatsapp/d/e$a
    //   2040	2052	3863	com/whatsapp/d/e$a
    //   2092	2095	3863	com/whatsapp/d/e$a
    //   2137	2143	3863	com/whatsapp/d/e$a
    //   2183	2189	3863	com/whatsapp/d/e$a
    //   2229	2239	3863	com/whatsapp/d/e$a
    //   2279	2284	3863	com/whatsapp/d/e$a
    //   2362	2373	3863	com/whatsapp/d/e$a
    //   2413	2422	3863	com/whatsapp/d/e$a
    //   2462	2473	3863	com/whatsapp/d/e$a
    //   2513	2523	3863	com/whatsapp/d/e$a
    //   2563	2572	3863	com/whatsapp/d/e$a
    //   2626	2636	3863	com/whatsapp/d/e$a
    //   2676	2686	3863	com/whatsapp/d/e$a
    //   2726	2732	3863	com/whatsapp/d/e$a
    //   2772	2781	3863	com/whatsapp/d/e$a
    //   2821	2826	3863	com/whatsapp/d/e$a
    //   2925	2938	3863	com/whatsapp/d/e$a
    //   2978	2988	3863	com/whatsapp/d/e$a
    //   3028	3040	3863	com/whatsapp/d/e$a
    //   3080	3101	3863	com/whatsapp/d/e$a
    //   3141	3150	3863	com/whatsapp/d/e$a
    //   3198	3204	3863	com/whatsapp/d/e$a
    //   3255	3261	3863	com/whatsapp/d/e$a
    //   3301	3319	3863	com/whatsapp/d/e$a
    //   3359	3368	3863	com/whatsapp/d/e$a
    //   3416	3425	3863	com/whatsapp/d/e$a
    //   3484	3492	3863	com/whatsapp/d/e$a
    //   3542	3551	3863	com/whatsapp/d/e$a
    //   3591	3601	3863	com/whatsapp/d/e$a
    //   3641	3646	3863	com/whatsapp/d/e$a
    //   3686	3698	3863	com/whatsapp/d/e$a
    //   3828	3860	3863	com/whatsapp/d/e$a
    //   3981	3990	3863	com/whatsapp/d/e$a
    //   4030	4043	3863	com/whatsapp/d/e$a
    //   4092	4098	3863	com/whatsapp/d/e$a
    //   4138	4143	3863	com/whatsapp/d/e$a
    //   4242	4254	3863	com/whatsapp/d/e$a
    //   4402	4412	3863	com/whatsapp/d/e$a
    //   4452	4458	3863	com/whatsapp/d/e$a
    //   4498	4503	3863	com/whatsapp/d/e$a
    //   4585	4595	3863	com/whatsapp/d/e$a
    //   4635	4641	3863	com/whatsapp/d/e$a
    //   4681	4686	3863	com/whatsapp/d/e$a
    //   4785	4813	3863	com/whatsapp/d/e$a
    //   4853	4858	3863	com/whatsapp/d/e$a
    //   4143	4148	4176	java/io/IOException
    //   4153	4158	4189	java/io/IOException
    //   3702	3722	4273	java/io/IOException
    //   3724	3736	4273	java/io/IOException
    //   4288	4293	4321	java/io/IOException
    //   4298	4303	4334	java/io/IOException
    //   3745	3781	4357	java/io/IOException
    //   4347	4354	4357	java/io/IOException
    //   4452	4458	4543	java/io/IOException
    //   4498	4503	4543	java/io/IOException
    //   4686	4691	4719	java/io/IOException
    //   4696	4701	4732	java/io/IOException
    //   4858	4863	4891	java/io/IOException
    //   4868	4873	4904	java/io/IOException
    //   1810	1815	4917	java/io/IOException
    //   1820	1825	4930	java/io/IOException
    //   2284	2289	4943	java/io/IOException
    //   2294	2299	4956	java/io/IOException
    //   4503	4508	4969	java/io/IOException
    //   4513	4518	4982	java/io/IOException
    //   478	483	4995	java/io/IOException
    //   488	493	5008	java/io/IOException
    //   3899	3904	5021	java/io/IOException
    //   3909	3914	5034	java/io/IOException
    //   176	188	5047	com/whatsapp/MediaDownloadConnection$ConnectionFailureException
    //   192	216	5047	com/whatsapp/MediaDownloadConnection$ConnectionFailureException
    //   216	226	5047	com/whatsapp/MediaDownloadConnection$ConnectionFailureException
    //   231	245	5047	com/whatsapp/MediaDownloadConnection$ConnectionFailureException
    //   520	596	5047	com/whatsapp/MediaDownloadConnection$ConnectionFailureException
    //   603	622	5047	com/whatsapp/MediaDownloadConnection$ConnectionFailureException
    //   656	670	5047	com/whatsapp/MediaDownloadConnection$ConnectionFailureException
    //   5183	5188	5225	java/io/IOException
    //   5193	5198	5238	java/io/IOException
    //   176	188	5251	finally
    //   192	216	5251	finally
    //   216	226	5251	finally
    //   231	245	5251	finally
    //   520	596	5251	finally
    //   603	622	5251	finally
    //   656	670	5251	finally
    //   5270	5275	5308	java/io/IOException
    //   5280	5285	5321	java/io/IOException
    //   261	268	5334	finally
    //   284	295	5334	finally
    //   311	324	5334	finally
    //   340	351	5334	finally
    //   367	377	5334	finally
    //   393	420	5334	finally
    //   638	649	5334	finally
    //   691	697	5334	finally
    //   713	718	5334	finally
    //   420	460	5356	finally
    //   735	755	5356	finally
    //   764	775	5356	finally
    //   793	805	5356	finally
    //   805	821	5356	finally
    //   1845	1856	5356	finally
    //   828	835	5367	finally
    //   835	855	5367	finally
    //   857	869	5367	finally
    //   1876	1902	5367	finally
    //   1945	1956	5367	finally
    //   909	916	5375	finally
    //   971	983	5375	finally
    //   1027	1036	5375	finally
    //   1076	1084	5375	finally
    //   1124	1136	5375	finally
    //   1176	1186	5375	finally
    //   1226	1235	5375	finally
    //   1275	1285	5375	finally
    //   1325	1339	5375	finally
    //   1383	1390	5375	finally
    //   1430	1439	5375	finally
    //   1479	1485	5375	finally
    //   1527	1542	5375	finally
    //   1582	1592	5375	finally
    //   1632	1647	5375	finally
    //   1687	1700	5375	finally
    //   1746	1758	5375	finally
    //   2040	2052	5375	finally
    //   2092	2095	5375	finally
    //   2137	2143	5375	finally
    //   2183	2189	5375	finally
    //   2229	2239	5375	finally
    //   2279	2284	5375	finally
    //   2362	2373	5375	finally
    //   2413	2422	5375	finally
    //   2462	2473	5375	finally
    //   2513	2523	5375	finally
    //   2563	2572	5375	finally
    //   2626	2636	5375	finally
    //   2676	2686	5375	finally
    //   2726	2732	5375	finally
    //   2772	2781	5375	finally
    //   2821	2826	5375	finally
    //   2925	2938	5375	finally
    //   2978	2988	5375	finally
    //   3028	3040	5375	finally
    //   3080	3101	5375	finally
    //   3141	3150	5375	finally
    //   3198	3204	5375	finally
    //   3255	3261	5375	finally
    //   3301	3319	5375	finally
    //   3359	3368	5375	finally
    //   3416	3425	5375	finally
    //   3484	3492	5375	finally
    //   3542	3551	5375	finally
    //   3591	3601	5375	finally
    //   3641	3646	5375	finally
    //   3686	3698	5375	finally
    //   3828	3860	5375	finally
    //   3889	3894	5375	finally
    //   3981	3990	5375	finally
    //   4030	4043	5375	finally
    //   4092	4098	5375	finally
    //   4138	4143	5375	finally
    //   4242	4254	5375	finally
    //   4402	4412	5375	finally
    //   4452	4458	5375	finally
    //   4498	4503	5375	finally
    //   4585	4595	5375	finally
    //   4635	4641	5375	finally
    //   4681	4686	5375	finally
    //   4785	4813	5375	finally
    //   4853	4858	5375	finally
    //   5077	5083	5375	finally
    //   5099	5155	5375	finally
    //   5171	5178	5375	finally
    //   3702	3722	5396	finally
    //   3724	3736	5396	finally
    //   4275	4288	5396	finally
    //   3745	3781	5401	finally
    //   4347	4354	5401	finally
    //   1771	1810	5414	finally
    //   468	473	5427	finally
    //   261	268	5432	com/whatsapp/MediaDownloadConnection$ConnectionFailureException
    //   284	295	5432	com/whatsapp/MediaDownloadConnection$ConnectionFailureException
    //   311	324	5432	com/whatsapp/MediaDownloadConnection$ConnectionFailureException
    //   340	351	5432	com/whatsapp/MediaDownloadConnection$ConnectionFailureException
    //   367	377	5432	com/whatsapp/MediaDownloadConnection$ConnectionFailureException
    //   393	420	5432	com/whatsapp/MediaDownloadConnection$ConnectionFailureException
    //   638	649	5432	com/whatsapp/MediaDownloadConnection$ConnectionFailureException
    //   691	697	5432	com/whatsapp/MediaDownloadConnection$ConnectionFailureException
    //   713	718	5432	com/whatsapp/MediaDownloadConnection$ConnectionFailureException
    //   420	460	5454	com/whatsapp/MediaDownloadConnection$ConnectionFailureException
    //   735	755	5454	com/whatsapp/MediaDownloadConnection$ConnectionFailureException
    //   764	775	5454	com/whatsapp/MediaDownloadConnection$ConnectionFailureException
    //   793	805	5454	com/whatsapp/MediaDownloadConnection$ConnectionFailureException
    //   805	821	5454	com/whatsapp/MediaDownloadConnection$ConnectionFailureException
    //   1845	1856	5454	com/whatsapp/MediaDownloadConnection$ConnectionFailureException
    //   828	835	5465	com/whatsapp/MediaDownloadConnection$ConnectionFailureException
    //   835	855	5465	com/whatsapp/MediaDownloadConnection$ConnectionFailureException
    //   857	869	5465	com/whatsapp/MediaDownloadConnection$ConnectionFailureException
    //   1876	1902	5465	com/whatsapp/MediaDownloadConnection$ConnectionFailureException
    //   1945	1956	5465	com/whatsapp/MediaDownloadConnection$ConnectionFailureException
    //   909	916	5473	com/whatsapp/MediaDownloadConnection$ConnectionFailureException
    //   971	983	5473	com/whatsapp/MediaDownloadConnection$ConnectionFailureException
    //   1027	1036	5473	com/whatsapp/MediaDownloadConnection$ConnectionFailureException
    //   1076	1084	5473	com/whatsapp/MediaDownloadConnection$ConnectionFailureException
    //   1124	1136	5473	com/whatsapp/MediaDownloadConnection$ConnectionFailureException
    //   1176	1186	5473	com/whatsapp/MediaDownloadConnection$ConnectionFailureException
    //   1226	1235	5473	com/whatsapp/MediaDownloadConnection$ConnectionFailureException
    //   1275	1285	5473	com/whatsapp/MediaDownloadConnection$ConnectionFailureException
    //   1325	1339	5473	com/whatsapp/MediaDownloadConnection$ConnectionFailureException
    //   1383	1390	5473	com/whatsapp/MediaDownloadConnection$ConnectionFailureException
    //   1430	1439	5473	com/whatsapp/MediaDownloadConnection$ConnectionFailureException
    //   1479	1485	5473	com/whatsapp/MediaDownloadConnection$ConnectionFailureException
    //   1527	1542	5473	com/whatsapp/MediaDownloadConnection$ConnectionFailureException
    //   1582	1592	5473	com/whatsapp/MediaDownloadConnection$ConnectionFailureException
    //   1632	1647	5473	com/whatsapp/MediaDownloadConnection$ConnectionFailureException
    //   1687	1700	5473	com/whatsapp/MediaDownloadConnection$ConnectionFailureException
    //   1746	1758	5473	com/whatsapp/MediaDownloadConnection$ConnectionFailureException
    //   2040	2052	5473	com/whatsapp/MediaDownloadConnection$ConnectionFailureException
    //   2092	2095	5473	com/whatsapp/MediaDownloadConnection$ConnectionFailureException
    //   2137	2143	5473	com/whatsapp/MediaDownloadConnection$ConnectionFailureException
    //   2183	2189	5473	com/whatsapp/MediaDownloadConnection$ConnectionFailureException
    //   2229	2239	5473	com/whatsapp/MediaDownloadConnection$ConnectionFailureException
    //   2279	2284	5473	com/whatsapp/MediaDownloadConnection$ConnectionFailureException
    //   2362	2373	5473	com/whatsapp/MediaDownloadConnection$ConnectionFailureException
    //   2413	2422	5473	com/whatsapp/MediaDownloadConnection$ConnectionFailureException
    //   2462	2473	5473	com/whatsapp/MediaDownloadConnection$ConnectionFailureException
    //   2513	2523	5473	com/whatsapp/MediaDownloadConnection$ConnectionFailureException
    //   2563	2572	5473	com/whatsapp/MediaDownloadConnection$ConnectionFailureException
    //   2626	2636	5473	com/whatsapp/MediaDownloadConnection$ConnectionFailureException
    //   2676	2686	5473	com/whatsapp/MediaDownloadConnection$ConnectionFailureException
    //   2726	2732	5473	com/whatsapp/MediaDownloadConnection$ConnectionFailureException
    //   2772	2781	5473	com/whatsapp/MediaDownloadConnection$ConnectionFailureException
    //   2821	2826	5473	com/whatsapp/MediaDownloadConnection$ConnectionFailureException
    //   2925	2938	5473	com/whatsapp/MediaDownloadConnection$ConnectionFailureException
    //   2978	2988	5473	com/whatsapp/MediaDownloadConnection$ConnectionFailureException
    //   3028	3040	5473	com/whatsapp/MediaDownloadConnection$ConnectionFailureException
    //   3080	3101	5473	com/whatsapp/MediaDownloadConnection$ConnectionFailureException
    //   3141	3150	5473	com/whatsapp/MediaDownloadConnection$ConnectionFailureException
    //   3198	3204	5473	com/whatsapp/MediaDownloadConnection$ConnectionFailureException
    //   3255	3261	5473	com/whatsapp/MediaDownloadConnection$ConnectionFailureException
    //   3301	3319	5473	com/whatsapp/MediaDownloadConnection$ConnectionFailureException
    //   3359	3368	5473	com/whatsapp/MediaDownloadConnection$ConnectionFailureException
    //   3416	3425	5473	com/whatsapp/MediaDownloadConnection$ConnectionFailureException
    //   3484	3492	5473	com/whatsapp/MediaDownloadConnection$ConnectionFailureException
    //   3542	3551	5473	com/whatsapp/MediaDownloadConnection$ConnectionFailureException
    //   3591	3601	5473	com/whatsapp/MediaDownloadConnection$ConnectionFailureException
    //   3641	3646	5473	com/whatsapp/MediaDownloadConnection$ConnectionFailureException
    //   3686	3698	5473	com/whatsapp/MediaDownloadConnection$ConnectionFailureException
    //   3828	3860	5473	com/whatsapp/MediaDownloadConnection$ConnectionFailureException
    //   3981	3990	5473	com/whatsapp/MediaDownloadConnection$ConnectionFailureException
    //   4030	4043	5473	com/whatsapp/MediaDownloadConnection$ConnectionFailureException
    //   4092	4098	5473	com/whatsapp/MediaDownloadConnection$ConnectionFailureException
    //   4138	4143	5473	com/whatsapp/MediaDownloadConnection$ConnectionFailureException
    //   4242	4254	5473	com/whatsapp/MediaDownloadConnection$ConnectionFailureException
    //   4402	4412	5473	com/whatsapp/MediaDownloadConnection$ConnectionFailureException
    //   4452	4458	5473	com/whatsapp/MediaDownloadConnection$ConnectionFailureException
    //   4498	4503	5473	com/whatsapp/MediaDownloadConnection$ConnectionFailureException
    //   4585	4595	5473	com/whatsapp/MediaDownloadConnection$ConnectionFailureException
    //   4635	4641	5473	com/whatsapp/MediaDownloadConnection$ConnectionFailureException
    //   4681	4686	5473	com/whatsapp/MediaDownloadConnection$ConnectionFailureException
    //   4785	4813	5473	com/whatsapp/MediaDownloadConnection$ConnectionFailureException
    //   4853	4858	5473	com/whatsapp/MediaDownloadConnection$ConnectionFailureException
    //   3702	3722	5486	com/whatsapp/MediaDownloadConnection$ConnectionFailureException
    //   3724	3736	5486	com/whatsapp/MediaDownloadConnection$ConnectionFailureException
    //   4275	4288	5486	com/whatsapp/MediaDownloadConnection$ConnectionFailureException
    //   3745	3781	5491	com/whatsapp/MediaDownloadConnection$ConnectionFailureException
    //   4347	4354	5491	com/whatsapp/MediaDownloadConnection$ConnectionFailureException
    //   1771	1810	5504	com/whatsapp/MediaDownloadConnection$ConnectionFailureException
    //   176	188	5517	com/whatsapp/d/e$a
    //   192	216	5517	com/whatsapp/d/e$a
    //   216	226	5517	com/whatsapp/d/e$a
    //   231	245	5517	com/whatsapp/d/e$a
    //   520	596	5517	com/whatsapp/d/e$a
    //   603	622	5517	com/whatsapp/d/e$a
    //   656	670	5517	com/whatsapp/d/e$a
    //   261	268	5534	com/whatsapp/d/e$a
    //   284	295	5534	com/whatsapp/d/e$a
    //   311	324	5534	com/whatsapp/d/e$a
    //   340	351	5534	com/whatsapp/d/e$a
    //   367	377	5534	com/whatsapp/d/e$a
    //   393	420	5534	com/whatsapp/d/e$a
    //   638	649	5534	com/whatsapp/d/e$a
    //   691	697	5534	com/whatsapp/d/e$a
    //   713	718	5534	com/whatsapp/d/e$a
    //   420	460	5552	com/whatsapp/d/e$a
    //   735	755	5552	com/whatsapp/d/e$a
    //   764	775	5552	com/whatsapp/d/e$a
    //   793	805	5552	com/whatsapp/d/e$a
    //   805	821	5552	com/whatsapp/d/e$a
    //   1845	1856	5552	com/whatsapp/d/e$a
    //   828	835	5563	com/whatsapp/d/e$a
    //   835	855	5563	com/whatsapp/d/e$a
    //   857	869	5563	com/whatsapp/d/e$a
    //   1876	1902	5563	com/whatsapp/d/e$a
    //   1945	1956	5563	com/whatsapp/d/e$a
    //   3702	3722	5571	com/whatsapp/d/e$a
    //   3724	3736	5571	com/whatsapp/d/e$a
    //   4275	4288	5571	com/whatsapp/d/e$a
    //   3745	3781	5576	com/whatsapp/d/e$a
    //   4347	4354	5576	com/whatsapp/d/e$a
    //   1771	1810	5585	com/whatsapp/d/e$a
    //   176	188	5594	com/whatsapp/m/e$a
    //   192	216	5594	com/whatsapp/m/e$a
    //   216	226	5594	com/whatsapp/m/e$a
    //   231	245	5594	com/whatsapp/m/e$a
    //   520	596	5594	com/whatsapp/m/e$a
    //   603	622	5594	com/whatsapp/m/e$a
    //   656	670	5594	com/whatsapp/m/e$a
    //   261	268	5611	com/whatsapp/m/e$a
    //   284	295	5611	com/whatsapp/m/e$a
    //   311	324	5611	com/whatsapp/m/e$a
    //   340	351	5611	com/whatsapp/m/e$a
    //   367	377	5611	com/whatsapp/m/e$a
    //   393	420	5611	com/whatsapp/m/e$a
    //   638	649	5611	com/whatsapp/m/e$a
    //   691	697	5611	com/whatsapp/m/e$a
    //   713	718	5611	com/whatsapp/m/e$a
    //   828	835	5629	com/whatsapp/m/e$a
    //   835	855	5629	com/whatsapp/m/e$a
    //   857	869	5629	com/whatsapp/m/e$a
    //   1876	1902	5629	com/whatsapp/m/e$a
    //   1945	1956	5629	com/whatsapp/m/e$a
    //   3702	3722	5637	com/whatsapp/m/e$a
    //   3724	3736	5637	com/whatsapp/m/e$a
    //   4275	4288	5637	com/whatsapp/m/e$a
    //   3745	3781	5642	com/whatsapp/m/e$a
    //   4347	4354	5642	com/whatsapp/m/e$a
    //   1771	1810	5651	com/whatsapp/m/e$a
    //   3702	3722	5660	com/whatsapp/m/e$b
    //   3724	3736	5660	com/whatsapp/m/e$b
    //   4275	4288	5660	com/whatsapp/m/e$b
    //   3745	3781	5665	com/whatsapp/m/e$b
    //   4347	4354	5665	com/whatsapp/m/e$b
    //   4275	4288	5674	java/io/IOException
    //   909	916	5699	com/whatsapp/m/e$a
    //   971	983	5699	com/whatsapp/m/e$a
    //   1027	1036	5699	com/whatsapp/m/e$a
    //   1076	1084	5699	com/whatsapp/m/e$a
    //   1124	1136	5699	com/whatsapp/m/e$a
    //   1176	1186	5699	com/whatsapp/m/e$a
    //   1226	1235	5699	com/whatsapp/m/e$a
    //   1275	1285	5699	com/whatsapp/m/e$a
    //   1325	1339	5699	com/whatsapp/m/e$a
    //   1383	1390	5699	com/whatsapp/m/e$a
    //   1430	1439	5699	com/whatsapp/m/e$a
    //   1479	1485	5699	com/whatsapp/m/e$a
    //   1527	1542	5699	com/whatsapp/m/e$a
    //   1582	1592	5699	com/whatsapp/m/e$a
    //   1632	1647	5699	com/whatsapp/m/e$a
    //   1687	1700	5699	com/whatsapp/m/e$a
    //   1746	1758	5699	com/whatsapp/m/e$a
    //   2040	2052	5699	com/whatsapp/m/e$a
    //   2092	2095	5699	com/whatsapp/m/e$a
    //   2137	2143	5699	com/whatsapp/m/e$a
    //   2183	2189	5699	com/whatsapp/m/e$a
    //   2229	2239	5699	com/whatsapp/m/e$a
    //   2279	2284	5699	com/whatsapp/m/e$a
    //   2362	2373	5699	com/whatsapp/m/e$a
    //   2413	2422	5699	com/whatsapp/m/e$a
    //   2462	2473	5699	com/whatsapp/m/e$a
    //   2513	2523	5699	com/whatsapp/m/e$a
    //   2563	2572	5699	com/whatsapp/m/e$a
    //   2626	2636	5699	com/whatsapp/m/e$a
    //   2676	2686	5699	com/whatsapp/m/e$a
    //   2726	2732	5699	com/whatsapp/m/e$a
    //   2772	2781	5699	com/whatsapp/m/e$a
    //   2821	2826	5699	com/whatsapp/m/e$a
    //   2925	2938	5699	com/whatsapp/m/e$a
    //   2978	2988	5699	com/whatsapp/m/e$a
    //   3028	3040	5699	com/whatsapp/m/e$a
    //   3080	3101	5699	com/whatsapp/m/e$a
    //   3141	3150	5699	com/whatsapp/m/e$a
    //   3198	3204	5699	com/whatsapp/m/e$a
    //   3255	3261	5699	com/whatsapp/m/e$a
    //   3301	3319	5699	com/whatsapp/m/e$a
    //   3359	3368	5699	com/whatsapp/m/e$a
    //   3416	3425	5699	com/whatsapp/m/e$a
    //   3484	3492	5699	com/whatsapp/m/e$a
    //   3542	3551	5699	com/whatsapp/m/e$a
    //   3591	3601	5699	com/whatsapp/m/e$a
    //   3641	3646	5699	com/whatsapp/m/e$a
    //   3686	3698	5699	com/whatsapp/m/e$a
    //   3828	3860	5699	com/whatsapp/m/e$a
    //   3981	3990	5699	com/whatsapp/m/e$a
    //   4030	4043	5699	com/whatsapp/m/e$a
    //   4092	4098	5699	com/whatsapp/m/e$a
    //   4138	4143	5699	com/whatsapp/m/e$a
    //   4242	4254	5699	com/whatsapp/m/e$a
    //   4402	4412	5699	com/whatsapp/m/e$a
    //   4452	4458	5699	com/whatsapp/m/e$a
    //   4498	4503	5699	com/whatsapp/m/e$a
    //   4585	4595	5699	com/whatsapp/m/e$a
    //   4635	4641	5699	com/whatsapp/m/e$a
    //   4681	4686	5699	com/whatsapp/m/e$a
    //   4785	4813	5699	com/whatsapp/m/e$a
    //   4853	4858	5699	com/whatsapp/m/e$a
  }
  
  static final class a
    extends Exception
  {}
  
  static final class b
    extends Exception
  {}
}


/* Location:              /home/chaitanya/sandbox/dex2jar-2.0/com.whatsapp-dex2jar.jar!/com/whatsapp/m/e.class
 * Java compiler version: 6 (50.0)
 * JD-Core Version:       0.7.1
 */