package com.whatsapp.data;

import android.content.Context;
import android.database.Cursor;
import android.database.sqlite.SQLiteDatabase;
import android.database.sqlite.SQLiteDatabaseCorruptException;
import android.database.sqlite.SQLiteStatement;
import android.text.TextUtils;
import com.whatsapp.ox;
import com.whatsapp.u;
import com.whatsapp.util.Log;
import com.whatsapp.vv;
import java.util.concurrent.locks.ReentrantReadWriteLock;
import java.util.concurrent.locks.ReentrantReadWriteLock.ReadLock;

public class y
{
  private static volatile y a;
  private final Context b;
  private final ox c;
  private final vv d;
  private final cn e;
  private final n f;
  private final ReentrantReadWriteLock.ReadLock g;
  
  private y(Context paramContext, ox paramox, vv paramvv, cn paramcn, ch paramch)
  {
    this.b = paramContext;
    this.c = paramox;
    this.d = paramvv;
    this.e = paramcn;
    this.f = paramch.a;
    this.g = paramch.b.readLock();
  }
  
  public static y a()
  {
    if (a == null) {}
    try
    {
      if (a == null) {
        a = new y(u.a(), ox.a(), vv.a(), cn.a(), ch.a());
      }
      return a;
    }
    finally {}
  }
  
  public final Cursor a(String paramString)
  {
    Log.i("mediamsgstore/getMediaMessagesCursor:" + paramString);
    this.g.lock();
    try
    {
      paramString = this.f.getReadableDatabase().rawQuery("SELECT key_from_me, key_id, status, needs_push, data, timestamp, media_url, media_mime_type, media_wa_type, media_size, media_name, media_caption, media_hash, media_duration, origin, latitude, longitude, thumb_image, remote_resource, raw_data, recipient_count, participant_hash, starred, quoted_row_id, mentioned_jids, multicast_id, edit_version, receipt_server_timestamp, media_enc_hash, _id FROM messages WHERE  media_wa_type in ('2' , '1' , '3' , '13' ) AND (origin IS NULL OR origin!=1) AND key_remote_jid=? ORDER BY _id DESC", new String[] { paramString });
      return paramString;
    }
    finally
    {
      this.g.unlock();
    }
  }
  
  public final Cursor a(String paramString, byte paramByte)
  {
    Log.d("mediamsgstore/getMediaMessagesByTypeCursor:" + paramString);
    this.g.lock();
    try
    {
      paramString = this.f.getReadableDatabase().rawQuery("SELECT key_from_me, key_id, status, needs_push, data, timestamp, media_url, media_mime_type, media_wa_type, media_size, media_name, media_caption, media_hash, media_duration, origin, latitude, longitude, thumb_image, remote_resource, raw_data, recipient_count, participant_hash, starred, quoted_row_id, mentioned_jids, multicast_id, edit_version, receipt_server_timestamp, media_enc_hash, _id FROM messages WHERE  media_wa_type=? AND key_remote_jid=? ORDER BY _id DESC", new String[] { Byte.toString(paramByte), paramString });
      return paramString;
    }
    finally
    {
      this.g.unlock();
    }
  }
  
  public final Cursor a(String paramString, long paramLong)
  {
    Log.i("mediamsgstore/getMediaMessagesHeadCursor:" + paramString);
    this.g.lock();
    try
    {
      paramString = this.f.getReadableDatabase().rawQuery("SELECT key_from_me, key_id, status, needs_push, data, timestamp, media_url, media_mime_type, media_wa_type, media_size, media_name, media_caption, media_hash, media_duration, origin, latitude, longitude, thumb_image, remote_resource, raw_data, recipient_count, participant_hash, starred, quoted_row_id, mentioned_jids, multicast_id, edit_version, receipt_server_timestamp, media_enc_hash, _id FROM messages WHERE  media_wa_type in ('2' , '1' , '3' , '13' ) AND (origin IS NULL OR origin!=1) AND key_remote_jid=?  AND _id<? ORDER BY _id DESC", new String[] { paramString, Long.toString(paramLong) });
      return paramString;
    }
    finally
    {
      this.g.unlock();
    }
  }
  
  public final Cursor a(String paramString, Byte[] paramArrayOfByte)
  {
    Log.d("mediamsgstore/getMediaMessagesByTypesCursor:" + paramString);
    this.g.lock();
    try
    {
      paramString = this.f.getReadableDatabase().rawQuery("SELECT key_from_me, key_id, status, needs_push, data, timestamp, media_url, media_mime_type, media_wa_type, media_size, media_name, media_caption, media_hash, media_duration, origin, latitude, longitude, thumb_image, remote_resource, raw_data, recipient_count, participant_hash, starred, quoted_row_id, mentioned_jids, multicast_id, edit_version, receipt_server_timestamp, media_enc_hash, _id FROM messages WHERE media_wa_type in (" + TextUtils.join(",", paramArrayOfByte) + ") AND key_remote_jid=? ORDER BY _id DESC", new String[] { paramString });
      return paramString;
    }
    finally
    {
      this.g.unlock();
    }
  }
  
  /* Error */
  public final com.whatsapp.MediaData a(String paramString, boolean paramBoolean)
  {
    // Byte code:
    //   0: invokestatic 170	a/a/a/a/a/a$d:c	()V
    //   3: aload_0
    //   4: getfield 48	com/whatsapp/data/y:g	Ljava/util/concurrent/locks/ReentrantReadWriteLock$ReadLock;
    //   7: invokevirtual 103	java/util/concurrent/locks/ReentrantReadWriteLock$ReadLock:lock	()V
    //   10: aload_0
    //   11: getfield 37	com/whatsapp/data/y:f	Lcom/whatsapp/data/n;
    //   14: astore 4
    //   16: aload 4
    //   18: getfield 173	com/whatsapp/data/n:b	Z
    //   21: ifne +38 -> 59
    //   24: aload 4
    //   26: getfield 176	com/whatsapp/data/n:a	Landroid/database/sqlite/SQLiteDatabase;
    //   29: ifnull +30 -> 59
    //   32: aload 4
    //   34: getfield 176	com/whatsapp/data/n:a	Landroid/database/sqlite/SQLiteDatabase;
    //   37: invokevirtual 180	android/database/sqlite/SQLiteDatabase:isOpen	()Z
    //   40: ifeq +19 -> 59
    //   43: aload 4
    //   45: getfield 176	com/whatsapp/data/n:a	Landroid/database/sqlite/SQLiteDatabase;
    //   48: ldc -74
    //   50: invokevirtual 185	android/database/sqlite/SQLiteDatabase:execSQL	(Ljava/lang/String;)V
    //   53: aload 4
    //   55: iconst_1
    //   56: putfield 173	com/whatsapp/data/n:b	Z
    //   59: aload_0
    //   60: getfield 37	com/whatsapp/data/y:f	Lcom/whatsapp/data/n;
    //   63: invokevirtual 109	com/whatsapp/data/n:getReadableDatabase	()Landroid/database/sqlite/SQLiteDatabase;
    //   66: ldc -69
    //   68: iconst_1
    //   69: anewarray 113	java/lang/String
    //   72: dup
    //   73: iconst_0
    //   74: aload_1
    //   75: aastore
    //   76: invokevirtual 119	android/database/sqlite/SQLiteDatabase:rawQuery	(Ljava/lang/String;[Ljava/lang/String;)Landroid/database/Cursor;
    //   79: astore 7
    //   81: aload 7
    //   83: ifnull +378 -> 461
    //   86: aload 7
    //   88: invokeinterface 192 1 0
    //   93: ifeq +361 -> 454
    //   96: aload 7
    //   98: iconst_0
    //   99: invokeinterface 196 2 0
    //   104: astore 4
    //   106: aload 4
    //   108: ifnull -22 -> 86
    //   111: new 198	java/io/ObjectInputStream
    //   114: dup
    //   115: new 200	java/io/ByteArrayInputStream
    //   118: dup
    //   119: aload 4
    //   121: invokespecial 203	java/io/ByteArrayInputStream:<init>	([B)V
    //   124: invokespecial 206	java/io/ObjectInputStream:<init>	(Ljava/io/InputStream;)V
    //   127: astore 5
    //   129: aload 5
    //   131: astore 6
    //   133: aload 5
    //   135: invokevirtual 210	java/io/ObjectInputStream:readObject	()Ljava/lang/Object;
    //   138: astore 4
    //   140: aload 5
    //   142: astore 6
    //   144: aload 4
    //   146: instanceof 212
    //   149: istore_3
    //   150: iload_3
    //   151: ifne +51 -> 202
    //   154: aload 5
    //   156: invokevirtual 215	java/io/ObjectInputStream:close	()V
    //   159: goto -73 -> 86
    //   162: astore 4
    //   164: aload 4
    //   166: invokestatic 218	com/whatsapp/util/Log:e	(Ljava/lang/Throwable;)V
    //   169: goto -83 -> 86
    //   172: astore_1
    //   173: aload_0
    //   174: getfield 25	com/whatsapp/data/y:b	Landroid/content/Context;
    //   177: invokestatic 224	a/a/a/a/d:h	(Landroid/content/Context;)V
    //   180: aload_1
    //   181: athrow
    //   182: astore_1
    //   183: aload 7
    //   185: invokeinterface 225 1 0
    //   190: aload_1
    //   191: athrow
    //   192: astore_1
    //   193: aload_0
    //   194: getfield 48	com/whatsapp/data/y:g	Ljava/util/concurrent/locks/ReentrantReadWriteLock$ReadLock;
    //   197: invokevirtual 122	java/util/concurrent/locks/ReentrantReadWriteLock$ReadLock:unlock	()V
    //   200: aload_1
    //   201: athrow
    //   202: aload 5
    //   204: astore 6
    //   206: aload 4
    //   208: checkcast 212	com/whatsapp/MediaData
    //   211: astore 4
    //   213: aload 5
    //   215: astore 6
    //   217: aload 4
    //   219: getfield 229	com/whatsapp/MediaData:file	Ljava/io/File;
    //   222: ifnull +101 -> 323
    //   225: aload 5
    //   227: astore 6
    //   229: aload 4
    //   231: getfield 232	com/whatsapp/MediaData:transferred	Z
    //   234: ifeq +89 -> 323
    //   237: aload 5
    //   239: astore 6
    //   241: aload 4
    //   243: getfield 229	com/whatsapp/MediaData:file	Ljava/io/File;
    //   246: invokevirtual 237	java/io/File:isAbsolute	()Z
    //   249: ifne +27 -> 276
    //   252: aload 5
    //   254: astore 6
    //   256: aload 4
    //   258: aload_0
    //   259: getfield 27	com/whatsapp/data/y:c	Lcom/whatsapp/ox;
    //   262: aload 4
    //   264: getfield 229	com/whatsapp/MediaData:file	Ljava/io/File;
    //   267: invokevirtual 240	java/io/File:getPath	()Ljava/lang/String;
    //   270: invokevirtual 243	com/whatsapp/ox:a	(Ljava/lang/String;)Ljava/io/File;
    //   273: putfield 229	com/whatsapp/MediaData:file	Ljava/io/File;
    //   276: aload 5
    //   278: astore 6
    //   280: aload 4
    //   282: getfield 229	com/whatsapp/MediaData:file	Ljava/io/File;
    //   285: invokevirtual 246	java/io/File:exists	()Z
    //   288: istore_3
    //   289: iload_3
    //   290: ifeq +33 -> 323
    //   293: aload 5
    //   295: invokevirtual 215	java/io/ObjectInputStream:close	()V
    //   298: aload 7
    //   300: invokeinterface 225 1 0
    //   305: aload_0
    //   306: getfield 48	com/whatsapp/data/y:g	Ljava/util/concurrent/locks/ReentrantReadWriteLock$ReadLock;
    //   309: invokevirtual 122	java/util/concurrent/locks/ReentrantReadWriteLock$ReadLock:unlock	()V
    //   312: aload 4
    //   314: areturn
    //   315: astore_1
    //   316: aload_1
    //   317: invokestatic 218	com/whatsapp/util/Log:e	(Ljava/lang/Throwable;)V
    //   320: goto -22 -> 298
    //   323: iload_2
    //   324: ifne +33 -> 357
    //   327: aload 5
    //   329: invokevirtual 215	java/io/ObjectInputStream:close	()V
    //   332: aload 7
    //   334: invokeinterface 225 1 0
    //   339: aload_0
    //   340: getfield 48	com/whatsapp/data/y:g	Ljava/util/concurrent/locks/ReentrantReadWriteLock$ReadLock;
    //   343: invokevirtual 122	java/util/concurrent/locks/ReentrantReadWriteLock$ReadLock:unlock	()V
    //   346: aload 4
    //   348: areturn
    //   349: astore_1
    //   350: aload_1
    //   351: invokestatic 218	com/whatsapp/util/Log:e	(Ljava/lang/Throwable;)V
    //   354: goto -22 -> 332
    //   357: aload 5
    //   359: invokevirtual 215	java/io/ObjectInputStream:close	()V
    //   362: goto -276 -> 86
    //   365: astore 4
    //   367: aload 4
    //   369: invokestatic 218	com/whatsapp/util/Log:e	(Ljava/lang/Throwable;)V
    //   372: goto -286 -> 86
    //   375: astore 4
    //   377: aconst_null
    //   378: astore 5
    //   380: aload 5
    //   382: astore 6
    //   384: new 80	java/lang/StringBuilder
    //   387: dup
    //   388: ldc -8
    //   390: invokespecial 85	java/lang/StringBuilder:<init>	(Ljava/lang/String;)V
    //   393: aload_1
    //   394: invokevirtual 89	java/lang/StringBuilder:append	(Ljava/lang/String;)Ljava/lang/StringBuilder;
    //   397: invokevirtual 93	java/lang/StringBuilder:toString	()Ljava/lang/String;
    //   400: aload 4
    //   402: invokestatic 251	com/whatsapp/util/Log:c	(Ljava/lang/String;Ljava/lang/Throwable;)V
    //   405: aload 5
    //   407: ifnull -321 -> 86
    //   410: aload 5
    //   412: invokevirtual 215	java/io/ObjectInputStream:close	()V
    //   415: goto -329 -> 86
    //   418: astore 4
    //   420: aload 4
    //   422: invokestatic 218	com/whatsapp/util/Log:e	(Ljava/lang/Throwable;)V
    //   425: goto -339 -> 86
    //   428: astore_1
    //   429: aconst_null
    //   430: astore 6
    //   432: aload 6
    //   434: ifnull +8 -> 442
    //   437: aload 6
    //   439: invokevirtual 215	java/io/ObjectInputStream:close	()V
    //   442: aload_1
    //   443: athrow
    //   444: astore 4
    //   446: aload 4
    //   448: invokestatic 218	com/whatsapp/util/Log:e	(Ljava/lang/Throwable;)V
    //   451: goto -9 -> 442
    //   454: aload 7
    //   456: invokeinterface 225 1 0
    //   461: aload_0
    //   462: getfield 48	com/whatsapp/data/y:g	Ljava/util/concurrent/locks/ReentrantReadWriteLock$ReadLock;
    //   465: invokevirtual 122	java/util/concurrent/locks/ReentrantReadWriteLock$ReadLock:unlock	()V
    //   468: aconst_null
    //   469: areturn
    //   470: astore_1
    //   471: goto -39 -> 432
    //   474: astore 4
    //   476: goto -96 -> 380
    //   479: astore 4
    //   481: aconst_null
    //   482: astore 5
    //   484: goto -104 -> 380
    //   487: astore 4
    //   489: goto -109 -> 380
    // Local variable table:
    //   start	length	slot	name	signature
    //   0	492	0	this	y
    //   0	492	1	paramString	String
    //   0	492	2	paramBoolean	boolean
    //   149	141	3	bool	boolean
    //   14	131	4	localObject	Object
    //   162	45	4	localIOException1	java.io.IOException
    //   211	136	4	localMediaData	com.whatsapp.MediaData
    //   365	3	4	localIOException2	java.io.IOException
    //   375	26	4	localClassNotFoundException1	ClassNotFoundException
    //   418	3	4	localIOException3	java.io.IOException
    //   444	3	4	localIOException4	java.io.IOException
    //   474	1	4	localClassNotFoundException2	ClassNotFoundException
    //   479	1	4	localIOException5	java.io.IOException
    //   487	1	4	localIOException6	java.io.IOException
    //   127	356	5	localObjectInputStream1	java.io.ObjectInputStream
    //   131	307	6	localObjectInputStream2	java.io.ObjectInputStream
    //   79	376	7	localCursor	Cursor
    // Exception table:
    //   from	to	target	type
    //   154	159	162	java/io/IOException
    //   86	106	172	android/database/sqlite/SQLiteDiskIOException
    //   154	159	172	android/database/sqlite/SQLiteDiskIOException
    //   164	169	172	android/database/sqlite/SQLiteDiskIOException
    //   293	298	172	android/database/sqlite/SQLiteDiskIOException
    //   316	320	172	android/database/sqlite/SQLiteDiskIOException
    //   327	332	172	android/database/sqlite/SQLiteDiskIOException
    //   350	354	172	android/database/sqlite/SQLiteDiskIOException
    //   357	362	172	android/database/sqlite/SQLiteDiskIOException
    //   367	372	172	android/database/sqlite/SQLiteDiskIOException
    //   410	415	172	android/database/sqlite/SQLiteDiskIOException
    //   420	425	172	android/database/sqlite/SQLiteDiskIOException
    //   437	442	172	android/database/sqlite/SQLiteDiskIOException
    //   442	444	172	android/database/sqlite/SQLiteDiskIOException
    //   446	451	172	android/database/sqlite/SQLiteDiskIOException
    //   86	106	182	finally
    //   154	159	182	finally
    //   164	169	182	finally
    //   173	182	182	finally
    //   293	298	182	finally
    //   316	320	182	finally
    //   327	332	182	finally
    //   350	354	182	finally
    //   357	362	182	finally
    //   367	372	182	finally
    //   410	415	182	finally
    //   420	425	182	finally
    //   437	442	182	finally
    //   442	444	182	finally
    //   446	451	182	finally
    //   10	59	192	finally
    //   59	81	192	finally
    //   183	192	192	finally
    //   298	305	192	finally
    //   332	339	192	finally
    //   454	461	192	finally
    //   293	298	315	java/io/IOException
    //   327	332	349	java/io/IOException
    //   357	362	365	java/io/IOException
    //   111	129	375	java/lang/ClassNotFoundException
    //   410	415	418	java/io/IOException
    //   111	129	428	finally
    //   437	442	444	java/io/IOException
    //   133	140	470	finally
    //   144	150	470	finally
    //   206	213	470	finally
    //   217	225	470	finally
    //   229	237	470	finally
    //   241	252	470	finally
    //   256	276	470	finally
    //   280	289	470	finally
    //   384	405	470	finally
    //   133	140	474	java/lang/ClassNotFoundException
    //   144	150	474	java/lang/ClassNotFoundException
    //   206	213	474	java/lang/ClassNotFoundException
    //   217	225	474	java/lang/ClassNotFoundException
    //   229	237	474	java/lang/ClassNotFoundException
    //   241	252	474	java/lang/ClassNotFoundException
    //   256	276	474	java/lang/ClassNotFoundException
    //   280	289	474	java/lang/ClassNotFoundException
    //   111	129	479	java/io/IOException
    //   133	140	487	java/io/IOException
    //   144	150	487	java/io/IOException
    //   206	213	487	java/io/IOException
    //   217	225	487	java/io/IOException
    //   229	237	487	java/io/IOException
    //   241	252	487	java/io/IOException
    //   256	276	487	java/io/IOException
    //   280	289	487	java/io/IOException
  }
  
  public final boolean a(String paramString, int paramInt)
  {
    this.g.lock();
    for (;;)
    {
      try
      {
        i = b(paramString);
        if (i == 0)
        {
          localSQLiteStatement = this.e.j;
          localSQLiteStatement.bindString(1, paramString);
          localSQLiteStatement.bindLong(2, paramInt);
          localSQLiteStatement.execute();
        }
      }
      finally
      {
        int i;
        SQLiteStatement localSQLiteStatement;
        this.g.unlock();
      }
      try
      {
        this.e.k.execute();
        this.g.unlock();
        return true;
      }
      catch (SQLiteDatabaseCorruptException paramString)
      {
        Log.d("msgstore/increment-ref-count", paramString);
        this.g.unlock();
      }
      localSQLiteStatement = this.e.k;
      localSQLiteStatement.bindLong(1, i + paramInt);
      localSQLiteStatement.bindString(2, paramString);
      localSQLiteStatement.execute();
    }
    return false;
  }
  
  /* Error */
  final int b(String paramString)
  {
    // Byte code:
    //   0: iconst_0
    //   1: istore_3
    //   2: aload_0
    //   3: getfield 48	com/whatsapp/data/y:g	Ljava/util/concurrent/locks/ReentrantReadWriteLock$ReadLock;
    //   6: invokevirtual 103	java/util/concurrent/locks/ReentrantReadWriteLock$ReadLock:lock	()V
    //   9: aload_0
    //   10: getfield 37	com/whatsapp/data/y:f	Lcom/whatsapp/data/n;
    //   13: invokevirtual 109	com/whatsapp/data/n:getReadableDatabase	()Landroid/database/sqlite/SQLiteDatabase;
    //   16: ldc_w 283
    //   19: iconst_1
    //   20: anewarray 113	java/lang/String
    //   23: dup
    //   24: iconst_0
    //   25: aload_1
    //   26: aastore
    //   27: invokevirtual 119	android/database/sqlite/SQLiteDatabase:rawQuery	(Ljava/lang/String;[Ljava/lang/String;)Landroid/database/Cursor;
    //   30: astore_1
    //   31: iload_3
    //   32: istore_2
    //   33: aload_1
    //   34: ifnull +22 -> 56
    //   37: iload_3
    //   38: istore_2
    //   39: aload_1
    //   40: invokeinterface 192 1 0
    //   45: ifeq +11 -> 56
    //   48: aload_1
    //   49: iconst_0
    //   50: invokeinterface 287 2 0
    //   55: istore_2
    //   56: aload_1
    //   57: ifnull +9 -> 66
    //   60: aload_1
    //   61: invokeinterface 225 1 0
    //   66: aload_0
    //   67: getfield 48	com/whatsapp/data/y:g	Ljava/util/concurrent/locks/ReentrantReadWriteLock$ReadLock;
    //   70: invokevirtual 122	java/util/concurrent/locks/ReentrantReadWriteLock$ReadLock:unlock	()V
    //   73: iload_2
    //   74: ireturn
    //   75: astore 4
    //   77: aload_0
    //   78: getfield 25	com/whatsapp/data/y:b	Landroid/content/Context;
    //   81: invokestatic 224	a/a/a/a/d:h	(Landroid/content/Context;)V
    //   84: aload 4
    //   86: athrow
    //   87: astore 4
    //   89: aload_1
    //   90: ifnull +9 -> 99
    //   93: aload_1
    //   94: invokeinterface 225 1 0
    //   99: aload 4
    //   101: athrow
    //   102: astore_1
    //   103: aload_0
    //   104: getfield 48	com/whatsapp/data/y:g	Ljava/util/concurrent/locks/ReentrantReadWriteLock$ReadLock;
    //   107: invokevirtual 122	java/util/concurrent/locks/ReentrantReadWriteLock$ReadLock:unlock	()V
    //   110: aload_1
    //   111: athrow
    // Local variable table:
    //   start	length	slot	name	signature
    //   0	112	0	this	y
    //   0	112	1	paramString	String
    //   32	42	2	i	int
    //   1	37	3	j	int
    //   75	10	4	localSQLiteDiskIOException	android.database.sqlite.SQLiteDiskIOException
    //   87	13	4	localObject	Object
    // Exception table:
    //   from	to	target	type
    //   39	56	75	android/database/sqlite/SQLiteDiskIOException
    //   39	56	87	finally
    //   77	87	87	finally
    //   9	31	102	finally
    //   60	66	102	finally
    //   93	99	102	finally
    //   99	102	102	finally
  }
  
  public final Cursor b(String paramString, long paramLong)
  {
    Log.i("mediamsgstore/getMediaMessagesTailCursor:" + paramString);
    this.g.lock();
    try
    {
      paramString = this.f.getReadableDatabase().rawQuery("SELECT key_from_me, key_id, status, needs_push, data, timestamp, media_url, media_mime_type, media_wa_type, media_size, media_name, media_caption, media_hash, media_duration, origin, latitude, longitude, thumb_image, remote_resource, raw_data, recipient_count, participant_hash, starred, quoted_row_id, mentioned_jids, multicast_id, edit_version, receipt_server_timestamp, media_enc_hash, _id FROM messages WHERE  media_wa_type in ('2' , '1' , '3' , '13' ) AND (origin IS NULL OR origin!=1) AND key_remote_jid=?  AND _id>? ORDER BY _id ASC", new String[] { paramString, Long.toString(paramLong) });
      return paramString;
    }
    finally
    {
      this.g.unlock();
    }
  }
}


/* Location:              /home/chaitanya/sandbox/dex2jar-2.0/com.whatsapp-dex2jar.jar!/com/whatsapp/data/y.class
 * Java compiler version: 6 (50.0)
 * JD-Core Version:       0.7.1
 */